{
  "id": 600,
  "name": "承德医学院",
  "level": "普通本科",
  "province": "河北",
  "year": 2025,
  "count": 15,
  "records": [
    {
      "school_id": 600,
      "name": "承德医学院",
      "year": 2025,
      "local_batch_id": 14,
      "local_batch_name": "本科批",
      "local_province_name": "内蒙古",
      "local_type_name": "物理类",
      "min": 486,
      "min_section": 33918,
      "num": 6,
      "proscore": 375,
      "sg_info": "首选物理，再选生物",
      "sg_name": "（001）",
      "special_group": "541801",
      "xclevel_name": "",
      "zslx_name": "普通类",
      "diff": 111,
      "local_type_id": 2073,
      "local_province_id": 15
    },
    {
      "school_id": 600,
      "name": "承德医学院",
      "year": 2025,
      "local_batch_id": 14,
      "local_batch_name": "本科批",
      "local_province_name": "上海",
      "local_type_name": "综合",
      "min": 465,
      "min_section": 34206,
      "num": "-",
      "proscore": 402,
      "sg_info": "生物必选",
      "sg_name": "（01）",
      "special_group": "546563",
      "xclevel_name": "",
      "zslx_name": "普通类",
      "diff": 63,
      "local_type_id": 3,
      "local_province_id": 31
    },
    {
      "school_id": 600,
      "name": "承德医学院",
      "year": 2025,
      "local_batch_id": 14,
      "local_batch_name": "本科批",
      "local_province_name": "江苏",
      "local_type_name": "物理类",
      "min": 578,
      "min_section": 57591,
      "num": "-",
      "proscore": 463,
      "sg_info": "首选物理，再选化学",
      "sg_name": "（01）",
      "special_group": "549800",
      "xclevel_name": "",
      "zslx_name": "普通类",
      "diff": 115,
      "local_type_id": 2073,
      "local_province_id": 32
    },
    {
      "school_id": 600,
      "name": "承德医学院",
      "year": 2025,
      "local_batch_id": 1570,
      "local_batch_name": "普通类一段",
      "local_province_name": "山东",
      "local_type_name": "综合",
      "min": 489,
      "min_section": 214157,
      "num": 11,
      "proscore": 441,
      "sg_info": "",
      "sg_name": "",
      "special_group": "0",
      "xclevel_name": "",
      "zslx_name": "普通类",
      "diff": 48,
      "local_type_id": 3,
      "local_province_id": 37
    },
    {
      "school_id": 600,
      "name": "承德医学院",
      "year": 2025,
      "local_batch_id": 1570,
      "local_batch_name": "普通类一段",
      "local_province_name": "山东",
      "local_type_name": "综合",
      "min": 541,
      "min_section": 98621,
      "num": 3,
      "proscore": 441,
      "sg_info": "",
      "sg_name": "",
      "special_group": "0",
      "xclevel_name": "",
      "zslx_name": "护理类",
      "diff": 100,
      "local_type_id": 3,
      "local_province_id": 37
    },
    {
      "school_id": 600,
      "name": "承德医学院",
      "year": 2025,
      "local_batch_id": 14,
      "local_batch_name": "本科批",
      "local_province_name": "湖南",
      "local_type_name": "物理类",
      "min": 551,
      "min_section": 44253,
      "num": "-",
      "proscore": 405,
      "sg_info": "首选物理，再选化学",
      "sg_name": "（101）",
      "special_group": "585375",
      "xclevel_name": "",
      "zslx_name": "普通类",
      "diff": 146,
      "local_type_id": 2073,
      "local_province_id": 43
    },
    {
      "school_id": 600,
      "name": "承德医学院",
      "year": 2025,
      "local_batch_id": 14,
      "local_batch_name": "本科批",
      "local_province_name": "湖南",
      "local_type_name": "物理类",
      "min": 490,
      "min_section": 102293,
      "num": "-",
      "proscore": 405,
      "sg_info": "首选物理，再选生物",
      "sg_name": "（102）",
      "special_group": "585379",
      "xclevel_name": "",
      "zslx_name": "普通类",
      "diff": 85,
      "local_type_id": 2073,
      "local_province_id": 43
    },
    {
      "school_id": 600,
      "name": "承德医学院",
      "year": 2025,
      "local_batch_id": 14,
      "local_batch_name": "本科批",
      "local_province_name": "广东",
      "local_type_name": "物理类",
      "min": 550,
      "min_section": 81414,
      "num": 3,
      "proscore": 436,
      "sg_info": "首选物理，再选化学",
      "sg_name": "（202）",
      "special_group": "612732",
      "xclevel_name": "",
      "zslx_name": "普通类",
      "diff": 114,
      "local_type_id": 2073,
      "local_province_id": 44
    },
    {
      "school_id": 600,
      "name": "承德医学院",
      "year": 2025,
      "local_batch_id": 14,
      "local_batch_name": "本科批",
      "local_province_name": "广西",
      "local_type_name": "物理类",
      "min": 535,
      "min_section": 33123,
      "num": "-",
      "proscore": 370,
      "sg_info": "首选物理，再选化学",
      "sg_name": "（100）",
      "special_group": "593394",
      "xclevel_name": "",
      "zslx_name": "普通类",
      "diff": 165,
      "local_type_id": 2073,
      "local_province_id": 45
    },
    {
      "school_id": 600,
      "name": "承德医学院",
      "year": 2025,
      "local_batch_id": 14,
      "local_batch_name": "本科批",
      "local_province_name": "重庆",
      "local_type_name": "物理类",
      "min": 569,
      "min_section": 23142,
      "num": "-",
      "proscore": 425,
      "sg_info": "",
      "sg_name": "",
      "special_group": "0",
      "xclevel_name": "",
      "zslx_name": "普通类",
      "diff": 144,
      "local_type_id": 2073,
      "local_province_id": 50
    },
    {
      "school_id": 600,
      "name": "承德医学院",
      "year": 2025,
      "local_batch_id": 14,
      "local_batch_name": "本科批",
      "local_province_name": "重庆",
      "local_type_name": "物理类",
      "min": 523,
      "min_section": 47737,
      "num": "-",
      "proscore": 425,
      "sg_info": "",
      "sg_name": "",
      "special_group": "0",
      "xclevel_name": "",
      "zslx_name": "护理类",
      "diff": 98,
      "local_type_id": 2073,
      "local_province_id": 50
    },
    {
      "school_id": 600,
      "name": "承德医学院",
      "year": 2025,
      "local_batch_id": 47,
      "local_batch_name": "本科批B段",
      "local_province_name": "四川",
      "local_type_name": "物理类",
      "min": 567,
      "min_section": 48644,
      "num": "-",
      "proscore": 438,
      "sg_info": "首选物理，再选化学",
      "sg_name": "（101）",
      "special_group": "493121",
      "xclevel_name": "",
      "zslx_name": "普通类",
      "diff": 129,
      "local_type_id": 2073,
      "local_province_id": 51
    },
    {
      "school_id": 600,
      "name": "承德医学院",
      "year": 2025,
      "local_batch_id": 47,
      "local_batch_name": "本科批B段",
      "local_province_name": "四川",
      "local_type_name": "物理类",
      "min": 507,
      "min_section": 117870,
      "num": "-",
      "proscore": 438,
      "sg_info": "首选物理，再选生物",
      "sg_name": "（102）",
      "special_group": "493137",
      "xclevel_name": "",
      "zslx_name": "普通类",
      "diff": 69,
      "local_type_id": 2073,
      "local_province_id": 51
    },
    {
      "school_id": 600,
      "name": "承德医学院",
      "year": 2025,
      "local_batch_id": 3453,
      "local_batch_name": "本科批C段",
      "local_province_name": "甘肃",
      "local_type_name": "物理类",
      "min": 472,
      "min_section": 41085,
      "num": "-",
      "proscore": 374,
      "sg_info": "首选物理，再选生物",
      "sg_name": "（001）",
      "special_group": "601034",
      "xclevel_name": "",
      "zslx_name": "普通类",
      "diff": 98,
      "local_type_id": 2073,
      "local_province_id": 62
    },
    {
      "school_id": 600,
      "name": "承德医学院",
      "year": 2025,
      "local_batch_id": 14,
      "local_batch_name": "本科批",
      "local_province_name": "青海",
      "local_type_name": "物理类",
      "min": 406,
      "min_section": 12237,
      "num": "-",
      "proscore": 350,
      "sg_info": "",
      "sg_name": "",
      "special_group": "0",
      "xclevel_name": "",
      "zslx_name": "普通类",
      "diff": 56,
      "local_type_id": 2073,
      "local_province_id": 63
    }
  ]
}