{
  "id": 700,
  "name": "沧州职业技术学院",
  "level": "专科（高职）",
  "province": "河北",
  "year": 2025,
  "count": 19,
  "records": [
    {
      "school_id": 700,
      "name": "沧州职业技术学院",
      "year": 2025,
      "local_batch_id": 10,
      "local_batch_name": "专科批",
      "local_province_name": "河北",
      "local_type_name": "历史类",
      "min": 371,
      "min_section": 144787,
      "num": "-",
      "proscore": 200,
      "sg_info": "",
      "sg_name": "",
      "special_group": "0",
      "xclevel_name": "",
      "zslx_name": "普通类",
      "diff": 171,
      "local_type_id": 2074,
      "local_province_id": 13
    },
    {
      "school_id": 700,
      "name": "沧州职业技术学院",
      "year": 2025,
      "local_batch_id": 10,
      "local_batch_name": "专科批",
      "local_province_name": "河北",
      "local_type_name": "历史类",
      "min": 450,
      "min_section": 83390,
      "num": "-",
      "proscore": 200,
      "sg_info": "",
      "sg_name": "",
      "special_group": "0",
      "xclevel_name": "",
      "zslx_name": "献县学院",
      "diff": 250,
      "local_type_id": 2074,
      "local_province_id": 13
    },
    {
      "school_id": 700,
      "name": "沧州职业技术学院",
      "year": 2025,
      "local_batch_id": 10,
      "local_batch_name": "专科批",
      "local_province_name": "河北",
      "local_type_name": "历史类",
      "min": 449,
      "min_section": 84133,
      "num": "-",
      "proscore": 200,
      "sg_info": "",
      "sg_name": "",
      "special_group": "0",
      "xclevel_name": "",
      "zslx_name": "渤海校区",
      "diff": 249,
      "local_type_id": 2074,
      "local_province_id": 13
    },
    {
      "school_id": 700,
      "name": "沧州职业技术学院",
      "year": 2025,
      "local_batch_id": 10,
      "local_batch_name": "专科批",
      "local_province_name": "河北",
      "local_type_name": "历史类",
      "min": 444,
      "min_section": 87656,
      "num": "-",
      "proscore": 200,
      "sg_info": "",
      "sg_name": "",
      "special_group": "0",
      "xclevel_name": "",
      "zslx_name": "孟村学院",
      "diff": 244,
      "local_type_id": 2074,
      "local_province_id": 13
    },
    {
      "school_id": 700,
      "name": "沧州职业技术学院",
      "year": 2025,
      "local_batch_id": 10,
      "local_batch_name": "专科批",
      "local_province_name": "河北",
      "local_type_name": "历史类",
      "min": 392,
      "min_section": 127497,
      "num": "-",
      "proscore": 200,
      "sg_info": "",
      "sg_name": "",
      "special_group": "0",
      "xclevel_name": "",
      "zslx_name": "河间学院",
      "diff": 192,
      "local_type_id": 2074,
      "local_province_id": 13
    },
    {
      "school_id": 700,
      "name": "沧州职业技术学院",
      "year": 2025,
      "local_batch_id": 10,
      "local_batch_name": "专科批",
      "local_province_name": "河北",
      "local_type_name": "历史类",
      "min": 389,
      "min_section": 129959,
      "num": "-",
      "proscore": 200,
      "sg_info": "",
      "sg_name": "",
      "special_group": "0",
      "xclevel_name": "",
      "zslx_name": "任丘学院",
      "diff": 189,
      "local_type_id": 2074,
      "local_province_id": 13
    },
    {
      "school_id": 700,
      "name": "沧州职业技术学院",
      "year": 2025,
      "local_batch_id": 10,
      "local_batch_name": "专科批",
      "local_province_name": "河北",
      "local_type_name": "历史类",
      "min": 388,
      "min_section": 130790,
      "num": "-",
      "proscore": 200,
      "sg_info": "",
      "sg_name": "",
      "special_group": "0",
      "xclevel_name": "",
      "zslx_name": "肃宁学院",
      "diff": 188,
      "local_type_id": 2074,
      "local_province_id": 13
    },
    {
      "school_id": 700,
      "name": "沧州职业技术学院",
      "year": 2025,
      "local_batch_id": 10,
      "local_batch_name": "专科批",
      "local_province_name": "河北",
      "local_type_name": "历史类",
      "min": 358,
      "min_section": 155314,
      "num": "-",
      "proscore": 200,
      "sg_info": "",
      "sg_name": "",
      "special_group": "0",
      "xclevel_name": "",
      "zslx_name": "吴桥学院",
      "diff": 158,
      "local_type_id": 2074,
      "local_province_id": 13
    },
    {
      "school_id": 700,
      "name": "沧州职业技术学院",
      "year": 2025,
      "local_batch_id": 10,
      "local_batch_name": "专科批",
      "local_province_name": "河北",
      "local_type_name": "历史类",
      "min": 338,
      "min_section": 170874,
      "num": "-",
      "proscore": 200,
      "sg_info": "",
      "sg_name": "",
      "special_group": "0",
      "xclevel_name": "",
      "zslx_name": "中外合作办学",
      "diff": 138,
      "local_type_id": 2074,
      "local_province_id": 13
    },
    {
      "sp_name": "电气自动化技术",
      "remark": "",
      "min": "457",
      "min_section": "227077",
      "average": "-",
      "is_score_range": 2,
      "min_range": "-",
      "min_rank_range": "-",
      "zslx_name": "普通类",
      "sg_info": "首选物理，再选不限",
      "diff": 257,
      "lq_num": "-",
      "school_special_id": 1682546,
      "school_special_status": 2,
      "local_type_id": 2073,
      "local_province_id": 13,
      "local_batch_id": 10
    },
    {
      "sp_name": "动物医学",
      "remark": "",
      "min": "452",
      "min_section": "233839",
      "average": "-",
      "is_score_range": 2,
      "min_range": "-",
      "min_rank_range": "-",
      "zslx_name": "普通类",
      "sg_info": "首选物理，再选不限",
      "diff": 252,
      "lq_num": "-",
      "school_special_id": 1680016,
      "school_special_status": 1,
      "local_type_id": 2073,
      "local_province_id": 13,
      "local_batch_id": 10
    },
    {
      "sp_name": "电力系统自动化技术",
      "remark": "",
      "min": "451",
      "min_section": "235189",
      "average": "-",
      "is_score_range": 2,
      "min_range": "-",
      "min_rank_range": "-",
      "zslx_name": "普通类",
      "sg_info": "首选物理，再选不限",
      "diff": 251,
      "lq_num": "-",
      "school_special_id": 1680674,
      "school_special_status": 2,
      "local_type_id": 2073,
      "local_province_id": 13,
      "local_batch_id": 10
    },
    {
      "sp_name": "数字媒体技术",
      "remark": "",
      "min": "445",
      "min_section": "242920",
      "average": "-",
      "is_score_range": 2,
      "min_range": "-",
      "min_rank_range": "-",
      "zslx_name": "普通类",
      "sg_info": "首选物理，再选不限",
      "diff": 245,
      "lq_num": "-",
      "school_special_id": 1792857,
      "school_special_status": 2,
      "local_type_id": 2073,
      "local_province_id": 13,
      "local_batch_id": 10
    },
    {
      "sp_name": "宠物养护与驯导",
      "remark": "",
      "min": "443",
      "min_section": "245391",
      "average": "-",
      "is_score_range": 2,
      "min_range": "-",
      "min_rank_range": "-",
      "zslx_name": "普通类",
      "sg_info": "首选物理，再选不限",
      "diff": 243,
      "lq_num": "-",
      "school_special_id": 1680572,
      "school_special_status": 2,
      "local_type_id": 2073,
      "local_province_id": 13,
      "local_batch_id": 10
    },
    {
      "sp_name": "机电一体化技术",
      "remark": "",
      "min": "443",
      "min_section": "245391",
      "average": "-",
      "is_score_range": 2,
      "min_range": "-",
      "min_rank_range": "-",
      "zslx_name": "普通类",
      "sg_info": "首选物理，再选不限",
      "diff": 243,
      "lq_num": "-",
      "school_special_id": 1682537,
      "school_special_status": 1,
      "local_type_id": 2073,
      "local_province_id": 13,
      "local_batch_id": 10
    },
    {
      "sp_name": "宠物医疗技术",
      "remark": "",
      "min": "442",
      "min_section": "246657",
      "average": "-",
      "is_score_range": 2,
      "min_range": "-",
      "min_rank_range": "-",
      "zslx_name": "普通类",
      "sg_info": "首选物理，再选不限",
      "diff": 242,
      "lq_num": "-",
      "school_special_id": 1860128,
      "school_special_status": 1,
      "local_type_id": 2073,
      "local_province_id": 13,
      "local_batch_id": 10
    },
    {
      "sp_name": "机械制造及自动化",
      "remark": "",
      "min": "442",
      "min_section": "246657",
      "average": "-",
      "is_score_range": 2,
      "min_range": "-",
      "min_rank_range": "-",
      "zslx_name": "普通类",
      "sg_info": "首选物理，再选不限",
      "diff": 242,
      "lq_num": "-",
      "school_special_id": 1792858,
      "school_special_status": 2,
      "local_type_id": 2073,
      "local_province_id": 13,
      "local_batch_id": 10
    },
    {
      "sp_name": "电气自动化技术",
      "remark": "（献县学院）（在献县学院（献县）就读）",
      "min": "441",
      "min_section": "247903",
      "average": "-",
      "is_score_range": 2,
      "min_range": "-",
      "min_rank_range": "-",
      "zslx_name": "献县学院",
      "sg_info": "首选物理，再选不限",
      "diff": 241,
      "lq_num": "-",
      "school_special_id": 1682546,
      "school_special_status": 2,
      "local_type_id": 2073,
      "local_province_id": 13,
      "local_batch_id": 10
    },
    {
      "sp_name": "电气自动化技术",
      "remark": "（低空飞控方向）",
      "min": "440",
      "min_section": "249128",
      "average": "-",
      "is_score_range": 2,
      "min_range": "-",
      "min_rank_range": "-",
      "zslx_name": "普通类",
      "sg_info": "首选物理，再选不限",
      "diff": 240,
      "lq_num": "-",
      "school_special_id": 1682546,
      "school_special_status": 2,
      "local_type_id": 2073,
      "local_province_id": 13,
      "local_batch_id": 10
    }
  ]
}