{
  "id": 1710,
  "name": "兰州石化职业技术大学",
  "level": "普通本科",
  "province": "甘肃",
  "year": 2025,
  "count": 125,
  "records": [
    {
      "sp_name": "大数据与会计",
      "remark": "（高职本科）（高职本科，详情查阅院校招生章程或向院校咨询；兰州新区校区）",
      "min": "516",
      "min_section": "35525",
      "average": "-",
      "is_score_range": 2,
      "min_range": "-",
      "min_rank_range": "-",
      "zslx_name": "普通类",
      "sg_info": "历史必选",
      "diff": "-",
      "lq_num": "-",
      "sg_name": "（01）",
      "school_special_id": 2155543,
      "school_special_status": 1,
      "local_type_id": 3,
      "local_province_id": 12,
      "local_batch_id": 46
    },
    {
      "sp_name": "人工智能工程技术",
      "remark": "（高职本科）（高职本科，详情查阅院校招生章程或向院校咨询；兰州新区校区）",
      "min": "513",
      "min_section": "36409",
      "average": "-",
      "is_score_range": 2,
      "min_range": "-",
      "min_rank_range": "-",
      "zslx_name": "普通类",
      "sg_info": "物理必选",
      "diff": "-",
      "lq_num": "-",
      "sg_name": "（03）",
      "school_special_id": 2155561,
      "school_special_status": 1,
      "local_type_id": 3,
      "local_province_id": 12,
      "local_batch_id": 46
    },
    {
      "sp_name": "电子商务",
      "remark": "（高职本科）（高职本科，详情查阅院校招生章程或向院校咨询；兰州新区校区）",
      "min": "512",
      "min_section": "36711",
      "average": "-",
      "is_score_range": 2,
      "min_range": "-",
      "min_rank_range": "-",
      "zslx_name": "普通类",
      "sg_info": "历史必选",
      "diff": "-",
      "lq_num": "-",
      "sg_name": "（01）",
      "school_special_id": 2155542,
      "school_special_status": 1,
      "local_type_id": 3,
      "local_province_id": 12,
      "local_batch_id": 46
    },
    {
      "sp_name": "应用化工技术",
      "remark": "（高职本科）（高职本科，详情查阅院校招生章程或向院校咨询；西固西校区）",
      "min": "509",
      "min_section": "37624",
      "average": "-",
      "is_score_range": 2,
      "min_range": "-",
      "min_rank_range": "-",
      "zslx_name": "普通类",
      "sg_info": "物理、化学(2科必选)",
      "diff": "-",
      "lq_num": "-",
      "sg_name": "（02）",
      "school_special_id": 2155929,
      "school_special_status": 1,
      "local_type_id": 3,
      "local_province_id": 12,
      "local_batch_id": 46
    },
    {
      "sp_name": "化工智能制造工程技术",
      "remark": "（高职本科）（高职本科，详情查阅院校招生章程或向院校咨询；西固西校区）",
      "min": "502",
      "min_section": "39655",
      "average": "-",
      "is_score_range": 2,
      "min_range": "-",
      "min_rank_range": "-",
      "zslx_name": "普通类",
      "sg_info": "物理、化学(2科必选)",
      "diff": "-",
      "lq_num": "-",
      "sg_name": "（02）",
      "school_special_id": 2155548,
      "school_special_status": 1,
      "local_type_id": 3,
      "local_province_id": 12,
      "local_batch_id": 46
    },
    {
      "sp_name": "石油化工技术",
      "remark": "（兰州市）",
      "min": "471",
      "min_section": "206836",
      "average": "-",
      "is_score_range": 2,
      "min_range": "-",
      "min_rank_range": "-",
      "zslx_name": "普通类",
      "sg_info": "首选物理，再选不限",
      "diff": 271,
      "lq_num": "-",
      "school_special_id": 1716002,
      "school_special_status": 1,
      "local_type_id": 2073,
      "local_province_id": 13,
      "local_batch_id": 10
    },
    {
      "sp_name": "电气自动化技术",
      "remark": "（兰州市）",
      "min": "468",
      "min_section": "211317",
      "average": "-",
      "is_score_range": 2,
      "min_range": "-",
      "min_rank_range": "-",
      "zslx_name": "普通类",
      "sg_info": "首选物理，再选不限",
      "diff": 268,
      "lq_num": "-",
      "school_special_id": 126453,
      "school_special_status": 1,
      "local_type_id": 2073,
      "local_province_id": 13,
      "local_batch_id": 10
    },
    {
      "sp_name": "应用化工技术",
      "remark": "（兰州市）",
      "min": "467",
      "min_section": "212828",
      "average": "-",
      "is_score_range": 2,
      "min_range": "-",
      "min_rank_range": "-",
      "zslx_name": "普通类",
      "sg_info": "首选物理，再选不限",
      "diff": 267,
      "lq_num": "-",
      "school_special_id": 126449,
      "school_special_status": 1,
      "local_type_id": 2073,
      "local_province_id": 13,
      "local_batch_id": 10
    },
    {
      "sp_name": "石油炼制技术",
      "remark": "（兰州市）",
      "min": "466",
      "min_section": "214306",
      "average": "-",
      "is_score_range": 2,
      "min_range": "-",
      "min_rank_range": "-",
      "zslx_name": "普通类",
      "sg_info": "首选物理，再选不限",
      "diff": 266,
      "lq_num": "-",
      "school_special_id": 1741007,
      "school_special_status": 1,
      "local_type_id": 2073,
      "local_province_id": 13,
      "local_batch_id": 10
    },
    {
      "sp_name": "油气储运技术",
      "remark": "（兰州市）",
      "min": "458",
      "min_section": "225599",
      "average": "-",
      "is_score_range": 2,
      "min_range": "-",
      "min_rank_range": "-",
      "zslx_name": "普通类",
      "sg_info": "首选物理，再选不限",
      "diff": 258,
      "lq_num": "-",
      "school_special_id": 1712922,
      "school_special_status": 1,
      "local_type_id": 2073,
      "local_province_id": 13,
      "local_batch_id": 10
    },
    {
      "sp_name": "新能源汽车技术",
      "remark": "（兰州市）",
      "min": "456",
      "min_section": "228462",
      "average": "-",
      "is_score_range": 2,
      "min_range": "-",
      "min_rank_range": "-",
      "zslx_name": "普通类",
      "sg_info": "首选物理，再选不限",
      "diff": 256,
      "lq_num": "-",
      "school_special_id": 126463,
      "school_special_status": 1,
      "local_type_id": 2073,
      "local_province_id": 13,
      "local_batch_id": 10
    },
    {
      "sp_name": "高分子合成技术",
      "remark": "（兰州市）",
      "min": "453",
      "min_section": "232534",
      "average": "-",
      "is_score_range": 2,
      "min_range": "-",
      "min_rank_range": "-",
      "zslx_name": "普通类",
      "sg_info": "首选物理，再选不限",
      "diff": 253,
      "lq_num": "-",
      "school_special_id": 1615822,
      "school_special_status": 1,
      "local_type_id": 2073,
      "local_province_id": 13,
      "local_batch_id": 10
    },
    {
      "sp_name": "热能动力工程技术",
      "remark": "（兰州市）",
      "min": "445",
      "min_section": "242920",
      "average": "-",
      "is_score_range": 2,
      "min_range": "-",
      "min_rank_range": "-",
      "zslx_name": "普通类",
      "sg_info": "首选物理，再选不限",
      "diff": 245,
      "lq_num": "-",
      "school_special_id": 1798131,
      "school_special_status": 1,
      "local_type_id": 2073,
      "local_province_id": 13,
      "local_batch_id": 10
    },
    {
      "sp_name": "智能网联汽车技术",
      "remark": "（兰州市）",
      "min": "445",
      "min_section": "242920",
      "average": "-",
      "is_score_range": 2,
      "min_range": "-",
      "min_rank_range": "-",
      "zslx_name": "普通类",
      "sg_info": "首选物理，再选不限",
      "diff": 245,
      "lq_num": "-",
      "school_special_id": 1472812,
      "school_special_status": 1,
      "local_type_id": 2073,
      "local_province_id": 13,
      "local_batch_id": 10
    },
    {
      "sp_name": "光伏工程技术",
      "remark": "（兰州市）",
      "min": "441",
      "min_section": "247903",
      "average": "-",
      "is_score_range": 2,
      "min_range": "-",
      "min_rank_range": "-",
      "zslx_name": "普通类",
      "sg_info": "首选物理，再选不限",
      "diff": 241,
      "lq_num": "-",
      "school_special_id": 1799815,
      "school_special_status": 1,
      "local_type_id": 2073,
      "local_province_id": 13,
      "local_batch_id": 10
    },
    {
      "sp_name": "物联网工程技术",
      "remark": "",
      "min": "454",
      "min_section": "39384",
      "average": "-",
      "is_score_range": 2,
      "min_range": "-",
      "min_rank_range": "-",
      "zslx_name": "普通类",
      "sg_info": "首选物理，再选不限",
      "diff": 114,
      "lq_num": "1",
      "sg_name": "（002）",
      "school_special_id": 2155562,
      "school_special_status": 1,
      "local_type_id": 2073,
      "local_province_id": 22,
      "local_batch_id": 14
    },
    {
      "sp_name": "电气工程及自动化",
      "remark": "",
      "min": "451",
      "min_section": "40315",
      "average": "-",
      "is_score_range": 2,
      "min_range": "-",
      "min_rank_range": "-",
      "zslx_name": "普通类",
      "sg_info": "首选物理，再选不限",
      "diff": 111,
      "lq_num": "2",
      "sg_name": "（002）",
      "school_special_id": 2155557,
      "school_special_status": 1,
      "local_type_id": 2073,
      "local_province_id": 22,
      "local_batch_id": 14
    },
    {
      "sp_name": "油气储运工程",
      "remark": "",
      "min": "447",
      "min_section": "41575",
      "average": "-",
      "is_score_range": 2,
      "min_range": "-",
      "min_rank_range": "-",
      "zslx_name": "普通类",
      "sg_info": "首选物理，再选不限",
      "diff": 107,
      "lq_num": "2",
      "sg_name": "（002）",
      "school_special_id": 2155554,
      "school_special_status": 1,
      "local_type_id": 2073,
      "local_province_id": 22,
      "local_batch_id": 14
    },
    {
      "sp_name": "应用化工技术",
      "remark": "",
      "min": "432",
      "min_section": "46087",
      "average": "-",
      "is_score_range": 2,
      "min_range": "-",
      "min_rank_range": "-",
      "zslx_name": "普通类",
      "sg_info": "首选物理，再选化学",
      "diff": 92,
      "lq_num": "1",
      "sg_name": "（003）",
      "school_special_id": 2155929,
      "school_special_status": 1,
      "local_type_id": 2073,
      "local_province_id": 22,
      "local_batch_id": 14
    },
    {
      "sp_name": "现代分析测试技术",
      "remark": "",
      "min": "431",
      "min_section": "46398",
      "average": "-",
      "is_score_range": 2,
      "min_range": "-",
      "min_rank_range": "-",
      "zslx_name": "普通类",
      "sg_info": "首选物理，再选化学",
      "diff": 91,
      "lq_num": "2",
      "sg_name": "（003）",
      "school_special_id": 2155546,
      "school_special_status": 1,
      "local_type_id": 2073,
      "local_province_id": 22,
      "local_batch_id": 14
    },
    {
      "sp_name": "化工智能制造工程技术",
      "remark": "",
      "min": "430",
      "min_section": "46698",
      "average": "-",
      "is_score_range": 2,
      "min_range": "-",
      "min_rank_range": "-",
      "zslx_name": "普通类",
      "sg_info": "首选物理，再选化学",
      "diff": 90,
      "lq_num": "2",
      "sg_name": "（003）",
      "school_special_id": 2155548,
      "school_special_status": 1,
      "local_type_id": 2073,
      "local_province_id": 22,
      "local_batch_id": 14
    },
    {
      "sp_name": "应用化工技术",
      "remark": "（公用工程）",
      "min": "368",
      "min_section": "23160",
      "average": "-",
      "is_score_range": 2,
      "min_range": "-",
      "min_rank_range": "-",
      "zslx_name": "普通类",
      "sg_info": "首选历史，再选不限",
      "diff": 208,
      "lq_num": "2",
      "sg_name": "（004）",
      "school_special_id": 126449,
      "school_special_status": 1,
      "local_type_id": 2074,
      "local_province_id": 22,
      "local_batch_id": 10
    },
    {
      "sp_name": "分析检验技术",
      "remark": "",
      "min": "367",
      "min_section": "23239",
      "average": "-",
      "is_score_range": 2,
      "min_range": "-",
      "min_rank_range": "-",
      "zslx_name": "普通类",
      "sg_info": "首选历史，再选不限",
      "diff": 207,
      "lq_num": "2",
      "sg_name": "（004）",
      "school_special_id": 1712921,
      "school_special_status": 2,
      "local_type_id": 2074,
      "local_province_id": 22,
      "local_batch_id": 10
    },
    {
      "sp_name": "化工安全技术",
      "remark": "",
      "min": "365",
      "min_section": "23421",
      "average": "-",
      "is_score_range": 2,
      "min_range": "-",
      "min_rank_range": "-",
      "zslx_name": "普通类",
      "sg_info": "首选历史，再选不限",
      "diff": 205,
      "lq_num": "2",
      "sg_name": "（004）",
      "school_special_id": 1694139,
      "school_special_status": 1,
      "local_type_id": 2074,
      "local_province_id": 22,
      "local_batch_id": 10
    },
    {
      "sp_name": "发电厂及电力系统",
      "remark": "",
      "min": "358",
      "min_section": "24045",
      "average": "-",
      "is_score_range": 2,
      "min_range": "-",
      "min_rank_range": "-",
      "zslx_name": "普通类",
      "sg_info": "首选历史，再选不限",
      "diff": 198,
      "lq_num": "2",
      "sg_name": "（004）",
      "school_special_id": 126458,
      "school_special_status": 1,
      "local_type_id": 2074,
      "local_province_id": 22,
      "local_batch_id": 10
    },
    {
      "sp_name": "热能动力工程技术",
      "remark": "",
      "min": "354",
      "min_section": "24359",
      "average": "-",
      "is_score_range": 2,
      "min_range": "-",
      "min_rank_range": "-",
      "zslx_name": "普通类",
      "sg_info": "首选历史，再选不限",
      "diff": 194,
      "lq_num": "2",
      "sg_name": "（004）",
      "school_special_id": 1798131,
      "school_special_status": 1,
      "local_type_id": 2074,
      "local_province_id": 22,
      "local_batch_id": 10
    },
    {
      "sp_name": "理化测试与质检技术",
      "remark": "",
      "min": "352",
      "min_section": "24539",
      "average": "-",
      "is_score_range": 2,
      "min_range": "-",
      "min_rank_range": "-",
      "zslx_name": "普通类",
      "sg_info": "首选历史，再选不限",
      "diff": 192,
      "lq_num": "2",
      "sg_name": "（004）",
      "school_special_id": 1030910,
      "school_special_status": 1,
      "local_type_id": 2074,
      "local_province_id": 22,
      "local_batch_id": 10
    },
    {
      "sp_name": "电子商务",
      "remark": "",
      "min": "348",
      "min_section": "24863",
      "average": "-",
      "is_score_range": 2,
      "min_range": "-",
      "min_rank_range": "-",
      "zslx_name": "普通类",
      "sg_info": "首选历史，再选不限",
      "diff": 188,
      "lq_num": "2",
      "sg_name": "（004）",
      "school_special_id": 1672216,
      "school_special_status": 2,
      "local_type_id": 2074,
      "local_province_id": 22,
      "local_batch_id": 10
    },
    {
      "sp_name": "电气工程及自动化",
      "remark": "",
      "min": "446",
      "min_section": "51508",
      "average": "-",
      "is_score_range": 2,
      "min_range": "-",
      "min_rank_range": "-",
      "zslx_name": "普通类",
      "sg_info": "首选物理，再选不限",
      "diff": 86,
      "lq_num": "-",
      "sg_name": "（003）",
      "school_special_id": 2155557,
      "school_special_status": 1,
      "local_type_id": 2073,
      "local_province_id": 23,
      "local_batch_id": 14
    },
    {
      "sp_name": "应用化工技术",
      "remark": "",
      "min": "433",
      "min_section": "56516",
      "average": "-",
      "is_score_range": 2,
      "min_range": "-",
      "min_rank_range": "-",
      "zslx_name": "普通类",
      "sg_info": "首选物理，再选化学",
      "diff": 73,
      "lq_num": "-",
      "sg_name": "（004）",
      "school_special_id": 2155929,
      "school_special_status": 1,
      "local_type_id": 2073,
      "local_province_id": 23,
      "local_batch_id": 14
    },
    {
      "sp_name": "油气储运工程",
      "remark": "",
      "min": "430",
      "min_section": "57714",
      "average": "-",
      "is_score_range": 2,
      "min_range": "-",
      "min_rank_range": "-",
      "zslx_name": "普通类",
      "sg_info": "首选物理，再选不限",
      "diff": 70,
      "lq_num": "-",
      "sg_name": "（003）",
      "school_special_id": 2155554,
      "school_special_status": 1,
      "local_type_id": 2073,
      "local_province_id": 23,
      "local_batch_id": 14
    },
    {
      "sp_name": "智能制造工程技术",
      "remark": "",
      "min": "429",
      "min_section": "58069",
      "average": "-",
      "is_score_range": 2,
      "min_range": "-",
      "min_rank_range": "-",
      "zslx_name": "普通类",
      "sg_info": "首选物理，再选不限",
      "diff": 69,
      "lq_num": "-",
      "sg_name": "（003）",
      "school_special_id": 2155556,
      "school_special_status": 1,
      "local_type_id": 2073,
      "local_province_id": 23,
      "local_batch_id": 14
    },
    {
      "sp_name": "现代测控工程技术",
      "remark": "",
      "min": "428",
      "min_section": "58457",
      "average": "-",
      "is_score_range": 2,
      "min_range": "-",
      "min_rank_range": "-",
      "zslx_name": "普通类",
      "sg_info": "首选物理，再选不限",
      "diff": 68,
      "lq_num": "-",
      "sg_name": "（003）",
      "school_special_id": 2155558,
      "school_special_status": 1,
      "local_type_id": 2073,
      "local_province_id": 23,
      "local_batch_id": 14
    },
    {
      "sp_name": "高分子材料工程技术",
      "remark": "",
      "min": "424",
      "min_section": "60117",
      "average": "-",
      "is_score_range": 2,
      "min_range": "-",
      "min_rank_range": "-",
      "zslx_name": "普通类",
      "sg_info": "首选物理，再选化学",
      "diff": 64,
      "lq_num": "-",
      "sg_name": "（004）",
      "school_special_id": 2155547,
      "school_special_status": 1,
      "local_type_id": 2073,
      "local_province_id": 23,
      "local_batch_id": 14
    },
    {
      "sp_name": "汽车工程技术",
      "remark": "",
      "min": "418",
      "min_section": "62502",
      "average": "-",
      "is_score_range": 2,
      "min_range": "-",
      "min_rank_range": "-",
      "zslx_name": "普通类",
      "sg_info": "首选物理，再选不限",
      "diff": 58,
      "lq_num": "-",
      "sg_name": "（003）",
      "school_special_id": 2155563,
      "school_special_status": 1,
      "local_type_id": 2073,
      "local_province_id": 23,
      "local_batch_id": 14
    },
    {
      "sp_name": "物联网工程技术",
      "remark": "",
      "min": "416",
      "min_section": "63298",
      "average": "-",
      "is_score_range": 2,
      "min_range": "-",
      "min_rank_range": "-",
      "zslx_name": "普通类",
      "sg_info": "首选物理，再选不限",
      "diff": 56,
      "lq_num": "-",
      "sg_name": "（003）",
      "school_special_id": 2155562,
      "school_special_status": 1,
      "local_type_id": 2073,
      "local_province_id": 23,
      "local_batch_id": 14
    },
    {
      "sp_name": "测绘工程技术",
      "remark": "",
      "min": "415",
      "min_section": "63704",
      "average": "-",
      "is_score_range": 2,
      "min_range": "-",
      "min_rank_range": "-",
      "zslx_name": "普通类",
      "sg_info": "首选物理，再选不限",
      "diff": 55,
      "lq_num": "-",
      "sg_name": "（003）",
      "school_special_id": 2155564,
      "school_special_status": 1,
      "local_type_id": 2073,
      "local_province_id": 23,
      "local_batch_id": 14
    },
    {
      "sp_name": "现代精细化工技术",
      "remark": "",
      "min": "415",
      "min_section": "63704",
      "average": "-",
      "is_score_range": 2,
      "min_range": "-",
      "min_rank_range": "-",
      "zslx_name": "普通类",
      "sg_info": "首选物理，再选化学",
      "diff": 55,
      "lq_num": "-",
      "sg_name": "（004）",
      "school_special_id": 2155553,
      "school_special_status": 1,
      "local_type_id": 2073,
      "local_province_id": 23,
      "local_batch_id": 14
    },
    {
      "sp_name": "电子商务",
      "remark": "（兰州新区校区）",
      "min": "523",
      "min_section": "36050",
      "average": "-",
      "is_score_range": 2,
      "min_range": "-",
      "min_rank_range": "-",
      "zslx_name": "普通类",
      "sg_info": "首选历史，再选不限",
      "diff": 41,
      "lq_num": "1",
      "sg_name": "（01）",
      "school_special_id": 2155542,
      "school_special_status": 1,
      "local_type_id": 2074,
      "local_province_id": 32,
      "local_batch_id": 14
    },
    {
      "sp_name": "人工智能工程技术",
      "remark": "",
      "min": "502",
      "min_section": "132119",
      "average": "503",
      "is_score_range": 2,
      "min_range": "-",
      "min_rank_range": "-",
      "zslx_name": "普通类",
      "sg_info": "首选物理，再选不限",
      "diff": 41,
      "lq_num": "-",
      "sg_name": "（001）",
      "school_special_id": 2155561,
      "school_special_status": 1,
      "local_type_id": 2073,
      "local_province_id": 34,
      "local_batch_id": 14
    },
    {
      "sp_name": "化工智能制造工程技术",
      "remark": "",
      "min": "499",
      "min_section": "136506",
      "average": "506",
      "is_score_range": 2,
      "min_range": "-",
      "min_rank_range": "-",
      "zslx_name": "普通类",
      "sg_info": "首选物理，再选化学",
      "diff": 38,
      "lq_num": "-",
      "sg_name": "（002）",
      "school_special_id": 2155548,
      "school_special_status": 1,
      "local_type_id": 2073,
      "local_province_id": 34,
      "local_batch_id": 14
    },
    {
      "sp_name": "石油化工技术",
      "remark": "",
      "min": "463",
      "min_section": "188658",
      "average": "466",
      "is_score_range": 2,
      "min_range": "-",
      "min_rank_range": "-",
      "zslx_name": "普通类",
      "sg_info": "首选物理，再选不限",
      "diff": 263,
      "lq_num": "-",
      "sg_name": "（003）",
      "school_special_id": 126451,
      "school_special_status": 2,
      "local_type_id": 2073,
      "local_province_id": 34,
      "local_batch_id": 10
    },
    {
      "sp_name": "应用化工技术",
      "remark": "",
      "min": "457",
      "min_section": "196741",
      "average": "458",
      "is_score_range": 2,
      "min_range": "-",
      "min_rank_range": "-",
      "zslx_name": "普通类",
      "sg_info": "首选物理，再选不限",
      "diff": 257,
      "lq_num": "-",
      "sg_name": "（003）",
      "school_special_id": 126449,
      "school_special_status": 1,
      "local_type_id": 2073,
      "local_province_id": 34,
      "local_batch_id": 10
    },
    {
      "sp_name": "材料工程技术",
      "remark": "",
      "min": "454",
      "min_section": "200651",
      "average": "454",
      "is_score_range": 2,
      "min_range": "-",
      "min_rank_range": "-",
      "zslx_name": "普通类",
      "sg_info": "首选物理，再选不限",
      "diff": 254,
      "lq_num": "-",
      "sg_name": "（003）",
      "school_special_id": 204687,
      "school_special_status": 2,
      "local_type_id": 2073,
      "local_province_id": 34,
      "local_batch_id": 10
    },
    {
      "sp_name": "电气自动化技术",
      "remark": "",
      "min": "447",
      "min_section": "209487",
      "average": "448",
      "is_score_range": 2,
      "min_range": "-",
      "min_rank_range": "-",
      "zslx_name": "普通类",
      "sg_info": "首选物理，再选不限",
      "diff": 247,
      "lq_num": "-",
      "sg_name": "（003）",
      "school_special_id": 126453,
      "school_special_status": 1,
      "local_type_id": 2073,
      "local_province_id": 34,
      "local_batch_id": 10
    },
    {
      "sp_name": "发电厂及电力系统",
      "remark": "",
      "min": "447",
      "min_section": "209487",
      "average": "453",
      "is_score_range": 2,
      "min_range": "-",
      "min_rank_range": "-",
      "zslx_name": "普通类",
      "sg_info": "首选物理，再选不限",
      "diff": 247,
      "lq_num": "-",
      "sg_name": "（003）",
      "school_special_id": 126458,
      "school_special_status": 1,
      "local_type_id": 2073,
      "local_province_id": 34,
      "local_batch_id": 10
    },
    {
      "sp_name": "理化测试与质检技术",
      "remark": "",
      "min": "445",
      "min_section": "211972",
      "average": "448",
      "is_score_range": 2,
      "min_range": "-",
      "min_rank_range": "-",
      "zslx_name": "普通类",
      "sg_info": "首选物理，再选不限",
      "diff": 245,
      "lq_num": "-",
      "sg_name": "（003）",
      "school_special_id": 1030910,
      "school_special_status": 1,
      "local_type_id": 2073,
      "local_province_id": 34,
      "local_batch_id": 10
    },
    {
      "sp_name": "化工装备技术",
      "remark": "",
      "min": "443",
      "min_section": "214395",
      "average": "448",
      "is_score_range": 2,
      "min_range": "-",
      "min_rank_range": "-",
      "zslx_name": "普通类",
      "sg_info": "首选物理，再选不限",
      "diff": 243,
      "lq_num": "-",
      "sg_name": "（003）",
      "school_special_id": 204686,
      "school_special_status": 1,
      "local_type_id": 2073,
      "local_province_id": 34,
      "local_batch_id": 10
    },
    {
      "sp_name": "热能动力工程技术",
      "remark": "",
      "min": "443",
      "min_section": "214395",
      "average": "444",
      "is_score_range": 2,
      "min_range": "-",
      "min_rank_range": "-",
      "zslx_name": "普通类",
      "sg_info": "首选物理，再选不限",
      "diff": 243,
      "lq_num": "-",
      "sg_name": "（003）",
      "school_special_id": 1798131,
      "school_special_status": 1,
      "local_type_id": 2073,
      "local_province_id": 34,
      "local_batch_id": 10
    },
    {
      "sp_name": "电气工程及自动化",
      "remark": "",
      "min": "502",
      "min_section": "67989",
      "average": "504",
      "is_score_range": 2,
      "min_range": "-",
      "min_rank_range": "-",
      "zslx_name": "普通类",
      "sg_info": "首选物理，再选不限",
      "diff": 61,
      "lq_num": "2",
      "sg_name": "（999）",
      "school_special_id": 2155557,
      "school_special_status": 1,
      "local_type_id": 2073,
      "local_province_id": 35,
      "local_batch_id": 14
    },
    {
      "sp_name": "应用化工技术",
      "remark": "",
      "min": "502",
      "min_section": "67989",
      "average": "508",
      "is_score_range": 2,
      "min_range": "-",
      "min_rank_range": "-",
      "zslx_name": "普通类",
      "sg_info": "首选物理，再选化学",
      "diff": 61,
      "lq_num": "3",
      "sg_name": "（500）",
      "school_special_id": 2155929,
      "school_special_status": 1,
      "local_type_id": 2073,
      "local_province_id": 35,
      "local_batch_id": 14
    },
    {
      "sp_name": "智能制造工程技术",
      "remark": "",
      "min": "498",
      "min_section": "71202",
      "average": "500",
      "is_score_range": 2,
      "min_range": "-",
      "min_rank_range": "-",
      "zslx_name": "普通类",
      "sg_info": "首选物理，再选不限",
      "diff": 57,
      "lq_num": "2",
      "sg_name": "（999）",
      "school_special_id": 2155556,
      "school_special_status": 1,
      "local_type_id": 2073,
      "local_province_id": 35,
      "local_batch_id": 14
    },
    {
      "sp_name": "现代精细化工技术",
      "remark": "",
      "min": "498",
      "min_section": "71202",
      "average": "500",
      "is_score_range": 2,
      "min_range": "-",
      "min_rank_range": "-",
      "zslx_name": "普通类",
      "sg_info": "首选物理，再选化学",
      "diff": 57,
      "lq_num": "2",
      "sg_name": "（500）",
      "school_special_id": 2155553,
      "school_special_status": 1,
      "local_type_id": 2073,
      "local_province_id": 35,
      "local_batch_id": 14
    },
    {
      "sp_name": "物联网工程技术",
      "remark": "",
      "min": "497",
      "min_section": "72041",
      "average": "498",
      "is_score_range": 2,
      "min_range": "-",
      "min_rank_range": "-",
      "zslx_name": "普通类",
      "sg_info": "首选物理，再选不限",
      "diff": 56,
      "lq_num": "2",
      "sg_name": "（999）",
      "school_special_id": 2155562,
      "school_special_status": 1,
      "local_type_id": 2073,
      "local_province_id": 35,
      "local_batch_id": 14
    },
    {
      "sp_name": "高分子材料工程技术",
      "remark": "",
      "min": "497",
      "min_section": "72041",
      "average": "501",
      "is_score_range": 2,
      "min_range": "-",
      "min_rank_range": "-",
      "zslx_name": "普通类",
      "sg_info": "首选物理，再选化学",
      "diff": 56,
      "lq_num": "2",
      "sg_name": "（500）",
      "school_special_id": 2155547,
      "school_special_status": 1,
      "local_type_id": 2073,
      "local_province_id": 35,
      "local_batch_id": 14
    },
    {
      "school_id": 1710,
      "name": "兰州石化职业技术大学",
      "year": 2025,
      "local_batch_id": 14,
      "local_batch_name": "本科批",
      "local_province_name": "河南",
      "local_type_name": "物理类",
      "min": 512,
      "min_section": 186510,
      "num": "-",
      "proscore": 427,
      "sg_info": "首选物理，再选不限",
      "sg_name": "（105）",
      "special_group": "505251",
      "xclevel_name": "",
      "zslx_name": "普通类",
      "diff": 85,
      "local_type_id": 2073,
      "local_province_id": 41
    },
    {
      "school_id": 1710,
      "name": "兰州石化职业技术大学",
      "year": 2025,
      "local_batch_id": 14,
      "local_batch_name": "本科批",
      "local_province_name": "河南",
      "local_type_name": "物理类",
      "min": 509,
      "min_section": 192194,
      "num": "-",
      "proscore": 427,
      "sg_info": "首选物理，再选化学",
      "sg_name": "（104）",
      "special_group": "505248",
      "xclevel_name": "",
      "zslx_name": "普通类",
      "diff": 82,
      "local_type_id": 2073,
      "local_province_id": 41
    },
    {
      "school_id": 1710,
      "name": "兰州石化职业技术大学",
      "year": 2025,
      "local_batch_id": 10,
      "local_batch_name": "专科批",
      "local_province_name": "河南",
      "local_type_name": "物理类",
      "min": 415,
      "min_section": 369055,
      "num": "-",
      "proscore": 185,
      "sg_info": "首选物理，再选不限",
      "sg_name": "（102）",
      "special_group": "505240",
      "xclevel_name": "",
      "zslx_name": "普通类",
      "diff": 230,
      "local_type_id": 2073,
      "local_province_id": 41
    },
    {
      "school_id": 1710,
      "name": "兰州石化职业技术大学",
      "year": 2025,
      "local_batch_id": 14,
      "local_batch_name": "本科批",
      "local_province_name": "河南",
      "local_type_name": "历史类",
      "min": 523,
      "min_section": 44282,
      "num": "-",
      "proscore": 471,
      "sg_info": "首选历史，再选不限",
      "sg_name": "（103）",
      "special_group": "505245",
      "xclevel_name": "",
      "zslx_name": "普通类",
      "diff": 52,
      "local_type_id": 2074,
      "local_province_id": 41
    },
    {
      "school_id": 1710,
      "name": "兰州石化职业技术大学",
      "year": 2025,
      "local_batch_id": 10,
      "local_batch_name": "专科批",
      "local_province_name": "河南",
      "local_type_name": "历史类",
      "min": 448,
      "min_section": 114784,
      "num": "-",
      "proscore": 185,
      "sg_info": "首选历史，再选不限",
      "sg_name": "（101）",
      "special_group": "505230",
      "xclevel_name": "",
      "zslx_name": "普通类",
      "diff": 263,
      "local_type_id": 2074,
      "local_province_id": 41
    },
    {
      "sp_name": "油气储运工程",
      "remark": "",
      "min": "525",
      "min_section": "162191",
      "average": "528",
      "is_score_range": 2,
      "min_range": "-",
      "min_rank_range": "-",
      "zslx_name": "普通类",
      "sg_info": "首选物理，再选不限",
      "diff": 98,
      "lq_num": "2",
      "sg_name": "（105）",
      "school_special_id": 2155554,
      "school_special_status": 1,
      "local_type_id": 2073,
      "local_province_id": 41,
      "local_batch_id": 14
    },
    {
      "sp_name": "电气工程及自动化",
      "remark": "",
      "min": "518",
      "min_section": "175267",
      "average": "522",
      "is_score_range": 2,
      "min_range": "-",
      "min_rank_range": "-",
      "zslx_name": "普通类",
      "sg_info": "首选物理，再选不限",
      "diff": 91,
      "lq_num": "2",
      "sg_name": "（105）",
      "school_special_id": 2155557,
      "school_special_status": 1,
      "local_type_id": 2073,
      "local_province_id": 41,
      "local_batch_id": 14
    },
    {
      "sp_name": "智能制造工程技术",
      "remark": "",
      "min": "516",
      "min_section": "178995",
      "average": "516",
      "is_score_range": 2,
      "min_range": "-",
      "min_rank_range": "-",
      "zslx_name": "普通类",
      "sg_info": "首选物理，再选不限",
      "diff": 89,
      "lq_num": "2",
      "sg_name": "（105）",
      "school_special_id": 2155556,
      "school_special_status": 1,
      "local_type_id": 2073,
      "local_province_id": 41,
      "local_batch_id": 14
    },
    {
      "sp_name": "汽车工程技术",
      "remark": "（办学地点：兰州新区校区）",
      "min": "513",
      "min_section": "184632",
      "average": "513",
      "is_score_range": 2,
      "min_range": "-",
      "min_rank_range": "-",
      "zslx_name": "普通类",
      "sg_info": "首选物理，再选不限",
      "diff": 86,
      "lq_num": "2",
      "sg_name": "（105）",
      "school_special_id": 2155563,
      "school_special_status": 1,
      "local_type_id": 2073,
      "local_province_id": 41,
      "local_batch_id": 14
    },
    {
      "sp_name": "物联网工程技术",
      "remark": "（办学地点：兰州新区校区）",
      "min": "513",
      "min_section": "184632",
      "average": "515",
      "is_score_range": 2,
      "min_range": "-",
      "min_rank_range": "-",
      "zslx_name": "普通类",
      "sg_info": "首选物理，再选不限",
      "diff": 86,
      "lq_num": "3",
      "sg_name": "（105）",
      "school_special_id": 2155562,
      "school_special_status": 1,
      "local_type_id": 2073,
      "local_province_id": 41,
      "local_batch_id": 14
    },
    {
      "sp_name": "现代测控工程技术",
      "remark": "",
      "min": "512",
      "min_section": "186510",
      "average": "512",
      "is_score_range": 2,
      "min_range": "-",
      "min_rank_range": "-",
      "zslx_name": "普通类",
      "sg_info": "首选物理，再选不限",
      "diff": 85,
      "lq_num": "2",
      "sg_name": "（105）",
      "school_special_id": 2155558,
      "school_special_status": 1,
      "local_type_id": 2073,
      "local_province_id": 41,
      "local_batch_id": 14
    },
    {
      "sp_name": "人工智能工程技术",
      "remark": "（办学地点：兰州新区校区）",
      "min": "512",
      "min_section": "186510",
      "average": "513",
      "is_score_range": 2,
      "min_range": "-",
      "min_rank_range": "-",
      "zslx_name": "普通类",
      "sg_info": "首选物理，再选不限",
      "diff": 85,
      "lq_num": "2",
      "sg_name": "（105）",
      "school_special_id": 2155561,
      "school_special_status": 1,
      "local_type_id": 2073,
      "local_province_id": 41,
      "local_batch_id": 14
    },
    {
      "sp_name": "应用化工技术",
      "remark": "（办学地点：西固西校区）",
      "min": "510",
      "min_section": "190228",
      "average": "518",
      "is_score_range": 2,
      "min_range": "-",
      "min_rank_range": "-",
      "zslx_name": "普通类",
      "sg_info": "首选物理，再选化学",
      "diff": 83,
      "lq_num": "2",
      "sg_name": "（104）",
      "school_special_id": 2155929,
      "school_special_status": 1,
      "local_type_id": 2073,
      "local_province_id": 41,
      "local_batch_id": 14
    },
    {
      "sp_name": "煤炭清洁利用工程",
      "remark": "（办学地点：西固西校区）",
      "min": "509",
      "min_section": "192194",
      "average": "528",
      "is_score_range": 2,
      "min_range": "-",
      "min_rank_range": "-",
      "zslx_name": "普通类",
      "sg_info": "首选物理，再选化学",
      "diff": 82,
      "lq_num": "2",
      "sg_name": "（104）",
      "school_special_id": 2155551,
      "school_special_status": 1,
      "local_type_id": 2073,
      "local_province_id": 41,
      "local_batch_id": 14
    },
    {
      "sp_name": "高分子材料工程技术",
      "remark": "（办学地点：西固西校区）",
      "min": "509",
      "min_section": "192194",
      "average": "510",
      "is_score_range": 2,
      "min_range": "-",
      "min_rank_range": "-",
      "zslx_name": "普通类",
      "sg_info": "首选物理，再选化学",
      "diff": 82,
      "lq_num": "2",
      "sg_name": "（104）",
      "school_special_id": 2155547,
      "school_special_status": 1,
      "local_type_id": 2073,
      "local_province_id": 41,
      "local_batch_id": 14
    },
    {
      "sp_name": "分析检验技术",
      "remark": "（办学地点：西固西校区）",
      "min": "459",
      "min_section": "289487",
      "average": "-",
      "is_score_range": 2,
      "min_range": "-",
      "min_rank_range": "-",
      "zslx_name": "普通类",
      "sg_info": "首选物理，再选不限",
      "diff": 274,
      "lq_num": "-",
      "sg_name": "（102）",
      "school_special_id": 1601084,
      "school_special_status": 1,
      "local_type_id": 2073,
      "local_province_id": 41,
      "local_batch_id": 10
    },
    {
      "sp_name": "石油化工技术",
      "remark": "（办学地点：西固西校区）",
      "min": "449",
      "min_section": "308332",
      "average": "-",
      "is_score_range": 2,
      "min_range": "-",
      "min_rank_range": "-",
      "zslx_name": "普通类",
      "sg_info": "首选物理，再选不限",
      "diff": 264,
      "lq_num": "-",
      "sg_name": "（102）",
      "school_special_id": 126451,
      "school_special_status": 2,
      "local_type_id": 2073,
      "local_province_id": 41,
      "local_batch_id": 10
    },
    {
      "sp_name": "油气储运技术",
      "remark": "",
      "min": "424",
      "min_section": "353511",
      "average": "-",
      "is_score_range": 2,
      "min_range": "-",
      "min_rank_range": "-",
      "zslx_name": "普通类",
      "sg_info": "首选物理，再选不限",
      "diff": 239,
      "lq_num": "-",
      "sg_name": "（102）",
      "school_special_id": 126456,
      "school_special_status": 2,
      "local_type_id": 2073,
      "local_province_id": 41,
      "local_batch_id": 10
    },
    {
      "sp_name": "电气自动化技术",
      "remark": "",
      "min": "424",
      "min_section": "353511",
      "average": "-",
      "is_score_range": 2,
      "min_range": "-",
      "min_rank_range": "-",
      "zslx_name": "普通类",
      "sg_info": "首选物理，再选不限",
      "diff": 239,
      "lq_num": "-",
      "sg_name": "（102）",
      "school_special_id": 126453,
      "school_special_status": 1,
      "local_type_id": 2073,
      "local_province_id": 41,
      "local_batch_id": 10
    },
    {
      "sp_name": "测绘地理信息技术",
      "remark": "（办学地点：兰州新区校区）",
      "min": "423",
      "min_section": "355229",
      "average": "-",
      "is_score_range": 2,
      "min_range": "-",
      "min_rank_range": "-",
      "zslx_name": "普通类",
      "sg_info": "首选物理，再选不限",
      "diff": 238,
      "lq_num": "-",
      "sg_name": "（102）",
      "school_special_id": 204694,
      "school_special_status": 1,
      "local_type_id": 2073,
      "local_province_id": 41,
      "local_batch_id": 10
    },
    {
      "sp_name": "工业自动化仪表技术",
      "remark": "",
      "min": "421",
      "min_section": "358710",
      "average": "-",
      "is_score_range": 2,
      "min_range": "-",
      "min_rank_range": "-",
      "zslx_name": "普通类",
      "sg_info": "首选物理，再选不限",
      "diff": 236,
      "lq_num": "-",
      "sg_name": "（102）",
      "school_special_id": 1798132,
      "school_special_status": 1,
      "local_type_id": 2073,
      "local_province_id": 41,
      "local_batch_id": 10
    },
    {
      "sp_name": "石油炼制技术",
      "remark": "（办学地点：西固西校区）",
      "min": "421",
      "min_section": "358710",
      "average": "-",
      "is_score_range": 2,
      "min_range": "-",
      "min_rank_range": "-",
      "zslx_name": "普通类",
      "sg_info": "首选物理，再选不限",
      "diff": 236,
      "lq_num": "-",
      "sg_name": "（102）",
      "school_special_id": 126452,
      "school_special_status": 2,
      "local_type_id": 2073,
      "local_province_id": 41,
      "local_batch_id": 10
    },
    {
      "sp_name": "应用化工技术",
      "remark": "（办学地点：西固西校区）",
      "min": "419",
      "min_section": "362154",
      "average": "-",
      "is_score_range": 2,
      "min_range": "-",
      "min_rank_range": "-",
      "zslx_name": "普通类",
      "sg_info": "首选物理，再选不限",
      "diff": 234,
      "lq_num": "-",
      "sg_name": "（102）",
      "school_special_id": 126449,
      "school_special_status": 1,
      "local_type_id": 2073,
      "local_province_id": 41,
      "local_batch_id": 10
    },
    {
      "sp_name": "化工安全技术",
      "remark": "（办学地点：西固西校区）",
      "min": "418",
      "min_section": "363912",
      "average": "-",
      "is_score_range": 2,
      "min_range": "-",
      "min_rank_range": "-",
      "zslx_name": "普通类",
      "sg_info": "首选物理，再选不限",
      "diff": 233,
      "lq_num": "-",
      "sg_name": "（102）",
      "school_special_id": 126454,
      "school_special_status": 2,
      "local_type_id": 2073,
      "local_province_id": 41,
      "local_batch_id": 10
    },
    {
      "sp_name": "发电厂及电力系统",
      "remark": "（办学地点：兰州新区校区）",
      "min": "418",
      "min_section": "363912",
      "average": "-",
      "is_score_range": 2,
      "min_range": "-",
      "min_rank_range": "-",
      "zslx_name": "普通类",
      "sg_info": "首选物理，再选不限",
      "diff": 233,
      "lq_num": "-",
      "sg_name": "（102）",
      "school_special_id": 126458,
      "school_special_status": 1,
      "local_type_id": 2073,
      "local_province_id": 41,
      "local_batch_id": 10
    },
    {
      "sp_name": "电气工程及自动化",
      "remark": "（办学地点：西固东校区）",
      "min": "528",
      "min_section": "62355",
      "average": "-",
      "is_score_range": 2,
      "min_range": "-",
      "min_rank_range": "-",
      "zslx_name": "普通类",
      "sg_info": "首选物理，再选不限",
      "diff": 102,
      "lq_num": "-",
      "sg_name": "（01）",
      "school_special_id": 2155557,
      "school_special_status": 1,
      "local_type_id": 2073,
      "local_province_id": 42,
      "local_batch_id": 14
    },
    {
      "sp_name": "现代分析测试技术",
      "remark": "（办学地点：西固西校区）",
      "min": "482",
      "min_section": "102491",
      "average": "-",
      "is_score_range": 2,
      "min_range": "-",
      "min_rank_range": "-",
      "zslx_name": "普通类",
      "sg_info": "首选物理，再选化学",
      "diff": 56,
      "lq_num": "-",
      "sg_name": "（02）",
      "school_special_id": 2155546,
      "school_special_status": 1,
      "local_type_id": 2073,
      "local_province_id": 42,
      "local_batch_id": 14
    },
    {
      "sp_name": "煤炭清洁利用工程",
      "remark": "（办学地点：西固西校区）",
      "min": "481",
      "min_section": "103356",
      "average": "-",
      "is_score_range": 2,
      "min_range": "-",
      "min_rank_range": "-",
      "zslx_name": "普通类",
      "sg_info": "首选物理，再选化学",
      "diff": 55,
      "lq_num": "-",
      "sg_name": "（02）",
      "school_special_id": 2155551,
      "school_special_status": 1,
      "local_type_id": 2073,
      "local_province_id": 42,
      "local_batch_id": 14
    },
    {
      "sp_name": "石油炼制技术",
      "remark": "",
      "min": "412",
      "min_section": "203076",
      "average": "-",
      "is_score_range": 2,
      "min_range": "-",
      "min_rank_range": "-",
      "zslx_name": "普通类",
      "sg_info": "首选物理，再选不限",
      "diff": 212,
      "lq_num": "-",
      "sg_name": "（105）",
      "school_special_id": 126452,
      "school_special_status": 2,
      "local_type_id": 2073,
      "local_province_id": 43,
      "local_batch_id": 10
    },
    {
      "sp_name": "理化测试与质检技术",
      "remark": "",
      "min": "410",
      "min_section": "205496",
      "average": "-",
      "is_score_range": 2,
      "min_range": "-",
      "min_rank_range": "-",
      "zslx_name": "普通类",
      "sg_info": "首选物理，再选不限",
      "diff": 210,
      "lq_num": "-",
      "sg_name": "（105）",
      "school_special_id": 1030910,
      "school_special_status": 1,
      "local_type_id": 2073,
      "local_province_id": 43,
      "local_batch_id": 10
    },
    {
      "sp_name": "电气自动化技术",
      "remark": "",
      "min": "408",
      "min_section": "207860",
      "average": "-",
      "is_score_range": 2,
      "min_range": "-",
      "min_rank_range": "-",
      "zslx_name": "普通类",
      "sg_info": "首选物理，再选不限",
      "diff": 208,
      "lq_num": "-",
      "sg_name": "（105）",
      "school_special_id": 126453,
      "school_special_status": 1,
      "local_type_id": 2073,
      "local_province_id": 43,
      "local_batch_id": 10
    },
    {
      "sp_name": "应用化工技术",
      "remark": "（公用工程）",
      "min": "401",
      "min_section": "216011",
      "average": "-",
      "is_score_range": 2,
      "min_range": "-",
      "min_rank_range": "-",
      "zslx_name": "普通类",
      "sg_info": "首选物理，再选不限",
      "diff": 201,
      "lq_num": "-",
      "sg_name": "（105）",
      "school_special_id": 126449,
      "school_special_status": 1,
      "local_type_id": 2073,
      "local_province_id": 43,
      "local_batch_id": 10
    },
    {
      "sp_name": "石油化工技术",
      "remark": "",
      "min": "397",
      "min_section": "220505",
      "average": "-",
      "is_score_range": 2,
      "min_range": "-",
      "min_rank_range": "-",
      "zslx_name": "普通类",
      "sg_info": "首选物理，再选不限",
      "diff": 197,
      "lq_num": "-",
      "sg_name": "（105）",
      "school_special_id": 126451,
      "school_special_status": 2,
      "local_type_id": 2073,
      "local_province_id": 43,
      "local_batch_id": 10
    },
    {
      "sp_name": "油气储运技术",
      "remark": "",
      "min": "396",
      "min_section": "221589",
      "average": "-",
      "is_score_range": 2,
      "min_range": "-",
      "min_rank_range": "-",
      "zslx_name": "普通类",
      "sg_info": "首选物理，再选不限",
      "diff": 196,
      "lq_num": "-",
      "sg_name": "（105）",
      "school_special_id": 126456,
      "school_special_status": 2,
      "local_type_id": 2073,
      "local_province_id": 43,
      "local_batch_id": 10
    },
    {
      "sp_name": "测绘地理信息技术",
      "remark": "",
      "min": "389",
      "min_section": "229013",
      "average": "-",
      "is_score_range": 2,
      "min_range": "-",
      "min_rank_range": "-",
      "zslx_name": "普通类",
      "sg_info": "首选物理，再选不限",
      "diff": 189,
      "lq_num": "-",
      "sg_name": "（105）",
      "school_special_id": 204694,
      "school_special_status": 1,
      "local_type_id": 2073,
      "local_province_id": 43,
      "local_batch_id": 10
    },
    {
      "sp_name": "化工装备技术",
      "remark": "",
      "min": "388",
      "min_section": "230066",
      "average": "-",
      "is_score_range": 2,
      "min_range": "-",
      "min_rank_range": "-",
      "zslx_name": "普通类",
      "sg_info": "首选物理，再选不限",
      "diff": 188,
      "lq_num": "-",
      "sg_name": "（105）",
      "school_special_id": 204686,
      "school_special_status": 1,
      "local_type_id": 2073,
      "local_province_id": 43,
      "local_batch_id": 10
    },
    {
      "sp_name": "水利水电工程技术",
      "remark": "",
      "min": "384",
      "min_section": "234145",
      "average": "-",
      "is_score_range": 2,
      "min_range": "-",
      "min_rank_range": "-",
      "zslx_name": "普通类",
      "sg_info": "首选物理，再选不限",
      "diff": 184,
      "lq_num": "-",
      "sg_name": "（105）",
      "school_special_id": 1030921,
      "school_special_status": 1,
      "local_type_id": 2073,
      "local_province_id": 43,
      "local_batch_id": 10
    },
    {
      "sp_name": "新能源汽车技术",
      "remark": "",
      "min": "383",
      "min_section": "235164",
      "average": "-",
      "is_score_range": 2,
      "min_range": "-",
      "min_rank_range": "-",
      "zslx_name": "普通类",
      "sg_info": "首选物理，再选不限",
      "diff": 183,
      "lq_num": "-",
      "sg_name": "（105）",
      "school_special_id": 126463,
      "school_special_status": 1,
      "local_type_id": 2073,
      "local_province_id": 43,
      "local_batch_id": 10
    },
    {
      "sp_name": "大数据与会计",
      "remark": "",
      "min": "485",
      "min_section": "33567",
      "average": "-",
      "is_score_range": 2,
      "min_range": "-",
      "min_rank_range": "-",
      "zslx_name": "普通类",
      "sg_info": "首选历史，再选不限",
      "diff": 39,
      "lq_num": "-",
      "sg_name": "（101）",
      "school_special_id": 2155543,
      "school_special_status": 1,
      "local_type_id": 2074,
      "local_province_id": 43,
      "local_batch_id": 14
    },
    {
      "sp_name": "电子商务",
      "remark": "",
      "min": "484",
      "min_section": "34000",
      "average": "-",
      "is_score_range": 2,
      "min_range": "-",
      "min_rank_range": "-",
      "zslx_name": "普通类",
      "sg_info": "首选历史，再选不限",
      "diff": 38,
      "lq_num": "-",
      "sg_name": "（101）",
      "school_special_id": 2155542,
      "school_special_status": 1,
      "local_type_id": 2074,
      "local_province_id": 43,
      "local_batch_id": 14
    },
    {
      "sp_name": "发电厂及电力系统",
      "remark": "（办学地点：兰州新区校区）",
      "min": "438",
      "min_section": "118296",
      "average": "-",
      "is_score_range": 2,
      "min_range": "-",
      "min_rank_range": "-",
      "zslx_name": "普通类",
      "sg_info": "首选历史，再选不限",
      "diff": 223,
      "lq_num": "2",
      "sg_name": "（503）",
      "school_special_id": 126458,
      "school_special_status": 1,
      "local_type_id": 2074,
      "local_province_id": 44,
      "local_batch_id": 10
    },
    {
      "sp_name": "热能动力工程技术",
      "remark": "（办学地点：兰州新区校区）",
      "min": "423",
      "min_section": "135749",
      "average": "-",
      "is_score_range": 2,
      "min_range": "-",
      "min_rank_range": "-",
      "zslx_name": "普通类",
      "sg_info": "首选历史，再选不限",
      "diff": 208,
      "lq_num": "2",
      "sg_name": "（503）",
      "school_special_id": 1798131,
      "school_special_status": 1,
      "local_type_id": 2074,
      "local_province_id": 44,
      "local_batch_id": 10
    },
    {
      "school_id": 1710,
      "name": "兰州石化职业技术大学",
      "year": 2025,
      "local_batch_id": 14,
      "local_batch_name": "本科批",
      "local_province_name": "广西",
      "local_type_name": "物理类",
      "min": 436,
      "min_section": 109666,
      "num": "-",
      "proscore": 370,
      "sg_info": "首选物理，再选不限",
      "sg_name": "（104）",
      "special_group": "595493",
      "xclevel_name": "",
      "zslx_name": "普通类",
      "diff": 66,
      "local_type_id": 2073,
      "local_province_id": 45
    },
    {
      "school_id": 1710,
      "name": "兰州石化职业技术大学",
      "year": 2025,
      "local_batch_id": 14,
      "local_batch_name": "本科批",
      "local_province_name": "广西",
      "local_type_name": "物理类",
      "min": 435,
      "min_section": 110643,
      "num": "-",
      "proscore": 370,
      "sg_info": "首选物理，再选化学",
      "sg_name": "（103）",
      "special_group": "595492",
      "xclevel_name": "",
      "zslx_name": "普通类",
      "diff": 65,
      "local_type_id": 2073,
      "local_province_id": 45
    },
    {
      "school_id": 1710,
      "name": "兰州石化职业技术大学",
      "year": 2025,
      "local_batch_id": 10,
      "local_batch_name": "专科批",
      "local_province_name": "广西",
      "local_type_name": "物理类",
      "min": 335,
      "min_section": 206835,
      "num": "-",
      "proscore": 200,
      "sg_info": "首选物理，再选不限",
      "sg_name": "（101）",
      "special_group": "595485",
      "xclevel_name": "",
      "zslx_name": "普通类",
      "diff": 135,
      "local_type_id": 2073,
      "local_province_id": 45
    },
    {
      "sp_name": "大数据与会计",
      "remark": "（在兰州新区校区办学）",
      "min": "454",
      "min_section": "31057",
      "average": "454",
      "is_score_range": 2,
      "min_range": "-",
      "min_rank_range": "-",
      "zslx_name": "普通类",
      "sg_info": "首选历史，再选不限",
      "diff": 52,
      "lq_num": "1",
      "sg_name": "（102）",
      "school_special_id": 2155543,
      "school_special_status": 1,
      "local_type_id": 2074,
      "local_province_id": 45,
      "local_batch_id": 14
    },
    {
      "school_id": 1710,
      "name": "兰州石化职业技术大学",
      "year": 2025,
      "local_batch_id": 14,
      "local_batch_name": "本科批",
      "local_province_name": "海南",
      "local_type_name": "综合",
      "min": 560,
      "min_section": 20915,
      "num": "-",
      "proscore": 480,
      "sg_info": "物理必选",
      "sg_name": "（01）",
      "special_group": "527046",
      "xclevel_name": "",
      "zslx_name": "普通类",
      "diff": 80,
      "local_type_id": 3,
      "local_province_id": 46
    },
    {
      "school_id": 1710,
      "name": "兰州石化职业技术大学",
      "year": 2025,
      "local_batch_id": 14,
      "local_batch_name": "本科批",
      "local_province_name": "海南",
      "local_type_name": "综合",
      "min": 531,
      "min_section": 28663,
      "num": "-",
      "proscore": 480,
      "sg_info": "物理、化学(2科必选)",
      "sg_name": "（02）",
      "special_group": "527049",
      "xclevel_name": "",
      "zslx_name": "普通类",
      "diff": 51,
      "local_type_id": 3,
      "local_province_id": 46
    },
    {
      "school_id": 1710,
      "name": "兰州石化职业技术大学",
      "year": 2025,
      "local_batch_id": 10,
      "local_batch_name": "专科批",
      "local_province_name": "海南",
      "local_type_name": "综合",
      "min": 467,
      "min_section": 46475,
      "num": "-",
      "proscore": 246,
      "sg_info": "不限",
      "sg_name": "（03）",
      "special_group": "527051",
      "xclevel_name": "",
      "zslx_name": "普通类",
      "diff": 221,
      "local_type_id": 3,
      "local_province_id": 46
    },
    {
      "sp_name": "人工智能工程技术",
      "remark": "",
      "min": "560",
      "min_section": "20915",
      "average": "-",
      "is_score_range": 2,
      "min_range": "-",
      "min_rank_range": "-",
      "zslx_name": "普通类",
      "sg_info": "物理必选",
      "diff": 80,
      "lq_num": "-",
      "sg_name": "（01）",
      "school_special_id": 2155561,
      "school_special_status": 1,
      "local_type_id": 3,
      "local_province_id": 46,
      "local_batch_id": 14
    },
    {
      "sp_name": "安全工程技术",
      "remark": "",
      "min": "531",
      "min_section": "28663",
      "average": "-",
      "is_score_range": 2,
      "min_range": "-",
      "min_rank_range": "-",
      "zslx_name": "普通类",
      "sg_info": "物理、化学(2科必选)",
      "diff": 51,
      "lq_num": "-",
      "sg_name": "（02）",
      "school_special_id": 2155552,
      "school_special_status": 1,
      "local_type_id": 3,
      "local_province_id": 46,
      "local_batch_id": 14
    },
    {
      "sp_name": "电气工程及自动化",
      "remark": "（办学地点：西固东校区）",
      "min": "527",
      "min_section": "45354",
      "average": "-",
      "is_score_range": 2,
      "min_range": "-",
      "min_rank_range": "-",
      "zslx_name": "普通类",
      "sg_info": "首选物理，再选不限",
      "diff": 102,
      "lq_num": "-",
      "school_special_id": 2155557,
      "school_special_status": 1,
      "local_type_id": 2073,
      "local_province_id": 50,
      "local_batch_id": 14
    },
    {
      "sp_name": "物联网工程技术",
      "remark": "（办学地点：兰州新区校区）",
      "min": "505",
      "min_section": "58929",
      "average": "-",
      "is_score_range": 2,
      "min_range": "-",
      "min_rank_range": "-",
      "zslx_name": "普通类",
      "sg_info": "首选物理，再选不限",
      "diff": 80,
      "lq_num": "-",
      "school_special_id": 2155562,
      "school_special_status": 1,
      "local_type_id": 2073,
      "local_province_id": 50,
      "local_batch_id": 14
    },
    {
      "school_id": 1710,
      "name": "兰州石化职业技术大学",
      "year": 2025,
      "local_batch_id": 47,
      "local_batch_name": "本科批B段",
      "local_province_name": "四川",
      "local_type_name": "历史类",
      "min": 528,
      "min_section": 31015,
      "num": "-",
      "proscore": 467,
      "sg_info": "首选历史，再选不限",
      "sg_name": "（101）",
      "special_group": "495538",
      "xclevel_name": "",
      "zslx_name": "普通类",
      "diff": 61,
      "local_type_id": 2074,
      "local_province_id": 51
    },
    {
      "school_id": 1710,
      "name": "兰州石化职业技术大学",
      "year": 2025,
      "local_batch_id": 10,
      "local_batch_name": "专科批",
      "local_province_name": "四川",
      "local_type_name": "历史类",
      "min": 431,
      "min_section": 95189,
      "num": "-",
      "proscore": 150,
      "sg_info": "首选历史，再选不限",
      "sg_name": "（101）",
      "special_group": "495529",
      "xclevel_name": "",
      "zslx_name": "普通类",
      "diff": 281,
      "local_type_id": 2074,
      "local_province_id": 51
    },
    {
      "school_id": 1710,
      "name": "兰州石化职业技术大学",
      "year": 2025,
      "local_batch_id": 10,
      "local_batch_name": "专科批",
      "local_province_name": "云南",
      "local_type_name": "历史类",
      "min": 424,
      "min_section": 62472,
      "num": 2,
      "proscore": 180,
      "sg_info": "首选历史，再选不限",
      "sg_name": "（01）",
      "special_group": "513599",
      "xclevel_name": "",
      "zslx_name": "普通类",
      "diff": 244,
      "local_type_id": 2074,
      "local_province_id": 53
    },
    {
      "school_id": 1710,
      "name": "兰州石化职业技术大学",
      "year": 2025,
      "local_batch_id": 3453,
      "local_batch_name": "本科批C段",
      "local_province_name": "甘肃",
      "local_type_name": "物理类",
      "min": 425,
      "min_section": 66451,
      "num": "-",
      "proscore": 374,
      "sg_info": "首选物理，再选化学",
      "sg_name": "（011）",
      "special_group": "603000",
      "xclevel_name": "",
      "zslx_name": "普通类",
      "diff": 51,
      "local_type_id": 2073,
      "local_province_id": 62
    },
    {
      "school_id": 1710,
      "name": "兰州石化职业技术大学",
      "year": 2025,
      "local_batch_id": 3453,
      "local_batch_name": "本科批C段",
      "local_province_name": "甘肃",
      "local_type_name": "物理类",
      "min": 423,
      "min_section": 67637,
      "num": "-",
      "proscore": 374,
      "sg_info": "首选物理，再选不限",
      "sg_name": "（010）",
      "special_group": "602999",
      "xclevel_name": "",
      "zslx_name": "普通类",
      "diff": 49,
      "local_type_id": 2073,
      "local_province_id": 62
    },
    {
      "school_id": 1710,
      "name": "兰州石化职业技术大学",
      "year": 2025,
      "local_batch_id": 3474,
      "local_batch_name": "专科批F段",
      "local_province_name": "甘肃",
      "local_type_name": "物理类",
      "min": 394,
      "min_section": 83835,
      "num": "-",
      "proscore": 180,
      "sg_info": "首选物理，再选不限",
      "sg_name": "（031）",
      "special_group": "603055",
      "xclevel_name": "",
      "zslx_name": "普通类",
      "diff": 214,
      "local_type_id": 2073,
      "local_province_id": 62
    },
    {
      "school_id": 1710,
      "name": "兰州石化职业技术大学",
      "year": 2025,
      "local_batch_id": 3453,
      "local_batch_name": "本科批C段",
      "local_province_name": "甘肃",
      "local_type_name": "物理类",
      "min": 440,
      "min_section": 58062,
      "num": "-",
      "proscore": 374,
      "sg_info": "首选物理，再选化学",
      "sg_name": "（023）",
      "special_group": "603039",
      "xclevel_name": "",
      "zslx_name": "地方专项计划",
      "diff": 66,
      "local_type_id": 2073,
      "local_province_id": 62
    },
    {
      "school_id": 1710,
      "name": "兰州石化职业技术大学",
      "year": 2025,
      "local_batch_id": 3453,
      "local_batch_name": "本科批C段",
      "local_province_name": "甘肃",
      "local_type_name": "物理类",
      "min": 434,
      "min_section": 61414,
      "num": "-",
      "proscore": 374,
      "sg_info": "首选物理，再选不限",
      "sg_name": "（022）",
      "special_group": "603036",
      "xclevel_name": "",
      "zslx_name": "地方专项计划",
      "diff": 60,
      "local_type_id": 2073,
      "local_province_id": 62
    },
    {
      "school_id": 1710,
      "name": "兰州石化职业技术大学",
      "year": 2025,
      "local_batch_id": 3453,
      "local_batch_name": "本科批C段",
      "local_province_name": "甘肃",
      "local_type_name": "物理类",
      "min": 411,
      "min_section": 74384,
      "num": "-",
      "proscore": 374,
      "sg_info": "首选物理，再选不限",
      "sg_name": "（902）",
      "special_group": "603071",
      "xclevel_name": "",
      "zslx_name": "预科",
      "diff": 37,
      "local_type_id": 2073,
      "local_province_id": 62
    },
    {
      "school_id": 1710,
      "name": "兰州石化职业技术大学",
      "year": 2025,
      "local_batch_id": 3453,
      "local_batch_name": "本科批C段",
      "local_province_name": "甘肃",
      "local_type_name": "物理类",
      "min": 401,
      "min_section": 80025,
      "num": "-",
      "proscore": 374,
      "sg_info": "首选物理，再选不限",
      "sg_name": "（018）",
      "special_group": "603025",
      "xclevel_name": "",
      "zslx_name": "少数民族紧缺人才培养专项",
      "diff": 27,
      "local_type_id": 2073,
      "local_province_id": 62
    },
    {
      "school_id": 1710,
      "name": "兰州石化职业技术大学",
      "year": 2025,
      "local_batch_id": 3453,
      "local_batch_name": "本科批C段",
      "local_province_name": "甘肃",
      "local_type_name": "物理类",
      "min": 400,
      "min_section": 80544,
      "num": "-",
      "proscore": 374,
      "sg_info": "首选物理，再选化学",
      "sg_name": "（019）",
      "special_group": "603028",
      "xclevel_name": "",
      "zslx_name": "藏区专项",
      "diff": 26,
      "local_type_id": 2073,
      "local_province_id": 62
    },
    {
      "school_id": 1710,
      "name": "兰州石化职业技术大学",
      "year": 2025,
      "local_batch_id": 3453,
      "local_batch_name": "本科批C段",
      "local_province_name": "甘肃",
      "local_type_name": "物理类",
      "min": 399,
      "min_section": 81090,
      "num": "-",
      "proscore": 374,
      "sg_info": "首选物理，再选化学",
      "sg_name": "（021）",
      "special_group": "603034",
      "xclevel_name": "",
      "zslx_name": "少数民族紧缺人才培养专项",
      "diff": 25,
      "local_type_id": 2073,
      "local_province_id": 62
    },
    {
      "school_id": 1710,
      "name": "兰州石化职业技术大学",
      "year": 2025,
      "local_batch_id": 3453,
      "local_batch_name": "本科批C段",
      "local_province_name": "甘肃",
      "local_type_name": "物理类",
      "min": 399,
      "min_section": 81090,
      "num": "-",
      "proscore": 374,
      "sg_info": "首选物理，再选不限",
      "sg_name": "（014）",
      "special_group": "603015",
      "xclevel_name": "",
      "zslx_name": "藏区专项",
      "diff": 25,
      "local_type_id": 2073,
      "local_province_id": 62
    },
    {
      "sp_name": "应用化工技术",
      "remark": "（南疆单列计划）",
      "min": "357",
      "min_section": "-",
      "average": "-",
      "is_score_range": 2,
      "min_range": "-",
      "min_rank_range": "-",
      "zslx_name": "南疆单列计划",
      "sg_info": "",
      "diff": "-",
      "lq_num": "-",
      "school_special_id": 2155929,
      "school_special_status": 1,
      "local_type_id": 1,
      "local_province_id": 65,
      "local_batch_id": 2895
    },
    {
      "sp_name": "现代测控工程技术",
      "remark": "（南疆单列计划）",
      "min": "353",
      "min_section": "-",
      "average": "-",
      "is_score_range": 2,
      "min_range": "-",
      "min_rank_range": "-",
      "zslx_name": "南疆单列计划",
      "sg_info": "",
      "diff": "-",
      "lq_num": "-",
      "school_special_id": 2155558,
      "school_special_status": 1,
      "local_type_id": 1,
      "local_province_id": 65,
      "local_batch_id": 2895
    },
    {
      "sp_name": "智能制造工程技术",
      "remark": "（南疆单列计划）",
      "min": "347",
      "min_section": "-",
      "average": "-",
      "is_score_range": 2,
      "min_range": "-",
      "min_rank_range": "-",
      "zslx_name": "南疆单列计划",
      "sg_info": "",
      "diff": "-",
      "lq_num": "-",
      "school_special_id": 2155556,
      "school_special_status": 1,
      "local_type_id": 1,
      "local_province_id": 65,
      "local_batch_id": 2895
    },
    {
      "sp_name": "数字媒体技术",
      "remark": "（南疆单列计划）",
      "min": "344",
      "min_section": "-",
      "average": "-",
      "is_score_range": 2,
      "min_range": "-",
      "min_rank_range": "-",
      "zslx_name": "南疆单列计划",
      "sg_info": "",
      "diff": "-",
      "lq_num": "-",
      "school_special_id": 2155560,
      "school_special_status": 1,
      "local_type_id": 1,
      "local_province_id": 65,
      "local_batch_id": 2895
    }
  ]
}