{
  "id": 2016,
  "name": "湖南机电职业技术学院",
  "level": "专科（高职）",
  "province": "湖南",
  "year": 2025,
  "count": 6,
  "records": [
    {
      "school_id": 2016,
      "name": "湖南机电职业技术学院",
      "year": 2025,
      "local_batch_id": 10,
      "local_batch_name": "专科批",
      "local_province_name": "山西",
      "local_type_name": "历史类",
      "min": 402,
      "min_section": 44799,
      "num": "-",
      "proscore": 100,
      "sg_info": "首选历史，再选不限",
      "sg_name": "（001）",
      "special_group": "536698",
      "xclevel_name": "",
      "zslx_name": "普通类",
      "diff": 302,
      "local_type_id": 2074,
      "local_province_id": 14
    },
    {
      "school_id": 2016,
      "name": "湖南机电职业技术学院",
      "year": 2025,
      "local_batch_id": 10,
      "local_batch_name": "专科批",
      "local_province_name": "内蒙古",
      "local_type_name": "历史类",
      "min": 401,
      "min_section": 22675,
      "num": 8,
      "proscore": 160,
      "sg_info": "首选历史，再选不限",
      "sg_name": "（001）",
      "special_group": "544003",
      "xclevel_name": "",
      "zslx_name": "普通类",
      "diff": 241,
      "local_type_id": 2074,
      "local_province_id": 15
    },
    {
      "sp_name": "电子商务",
      "remark": "",
      "min": "391",
      "min_section": "153255",
      "average": "405",
      "is_score_range": 2,
      "min_range": "-",
      "min_rank_range": "-",
      "zslx_name": "普通类",
      "sg_info": "首选物理，再选不限",
      "diff": 156,
      "lq_num": "6",
      "school_special_id": 68736,
      "school_special_status": 1,
      "local_type_id": 2073,
      "local_province_id": 35,
      "local_batch_id": 10
    },
    {
      "school_id": 2016,
      "name": "湖南机电职业技术学院",
      "year": 2025,
      "local_batch_id": 10,
      "local_batch_name": "专科批",
      "local_province_name": "江西",
      "local_type_name": "历史类",
      "min": 445,
      "min_section": 74405,
      "num": "-",
      "proscore": 290,
      "sg_info": "首选历史，再选不限",
      "sg_name": "（101）",
      "special_group": "571836",
      "xclevel_name": "",
      "zslx_name": "普通类",
      "diff": 155,
      "local_type_id": 2074,
      "local_province_id": 36
    },
    {
      "sp_name": "智能网联汽车技术",
      "remark": "",
      "min": "445",
      "min_section": "74405",
      "average": "-",
      "is_score_range": 2,
      "min_range": "-",
      "min_rank_range": "-",
      "zslx_name": "普通类",
      "sg_info": "首选历史，再选不限",
      "diff": 155,
      "lq_num": "4",
      "sg_name": "（101）",
      "school_special_id": 1472477,
      "school_special_status": 1,
      "local_type_id": 2074,
      "local_province_id": 36,
      "local_batch_id": 10
    },
    {
      "sp_name": "工业工程技术",
      "remark": "（办学地点：校本部）",
      "min": "380",
      "min_section": "346131",
      "average": "-",
      "is_score_range": 2,
      "min_range": "-",
      "min_rank_range": "-",
      "zslx_name": "普通类",
      "sg_info": "首选物理，再选不限",
      "diff": 180,
      "lq_num": "8",
      "sg_name": "（504）",
      "school_special_id": 1028779,
      "school_special_status": 1,
      "local_type_id": 2073,
      "local_province_id": 44,
      "local_batch_id": 10
    }
  ]
}