{
  "id": 2150,
  "name": "山东现代学院",
  "level": "普通本科",
  "province": "山东",
  "year": 2025,
  "count": 64,
  "records": [
    {
      "sp_name": "学前教育",
      "remark": "（师范类）",
      "min": "465",
      "min_section": "21324",
      "average": "-",
      "is_score_range": 2,
      "min_range": "-",
      "min_rank_range": "-",
      "zslx_name": "普通类",
      "sg_info": "首选历史，再选不限",
      "diff": 28,
      "lq_num": "1",
      "school_special_id": 159135,
      "school_special_status": 1,
      "local_type_id": 2074,
      "local_province_id": 21,
      "local_batch_id": 14
    },
    {
      "sp_name": "财务管理",
      "remark": "",
      "min": "462",
      "min_section": "21926",
      "average": "-",
      "is_score_range": 2,
      "min_range": "-",
      "min_rank_range": "-",
      "zslx_name": "普通类",
      "sg_info": "首选历史，再选不限",
      "diff": 25,
      "lq_num": "2",
      "school_special_id": 159151,
      "school_special_status": 1,
      "local_type_id": 2074,
      "local_province_id": 21,
      "local_batch_id": 14
    },
    {
      "sp_name": "物流管理",
      "remark": "",
      "min": "458",
      "min_section": "22672",
      "average": "-",
      "is_score_range": 2,
      "min_range": "-",
      "min_rank_range": "-",
      "zslx_name": "普通类",
      "sg_info": "首选历史，再选不限",
      "diff": 21,
      "lq_num": "1",
      "school_special_id": 159153,
      "school_special_status": 1,
      "local_type_id": 2074,
      "local_province_id": 21,
      "local_batch_id": 14
    },
    {
      "sp_name": "汉语国际教育",
      "remark": "",
      "min": "455",
      "min_section": "23282",
      "average": "-",
      "is_score_range": 2,
      "min_range": "-",
      "min_rank_range": "-",
      "zslx_name": "普通类",
      "sg_info": "首选历史，再选不限",
      "diff": 18,
      "lq_num": "4",
      "school_special_id": 159140,
      "school_special_status": 1,
      "local_type_id": 2074,
      "local_province_id": 21,
      "local_batch_id": 14
    },
    {
      "school_id": 2150,
      "name": "山东现代学院",
      "year": 2025,
      "local_batch_id": 14,
      "local_batch_name": "本科批",
      "local_province_name": "吉林",
      "local_type_name": "物理类",
      "min": 416,
      "min_section": 50809,
      "num": 2,
      "proscore": 340,
      "sg_info": "首选物理，再选生物",
      "sg_name": "（003）",
      "special_group": "482373",
      "xclevel_name": "",
      "zslx_name": "普通类",
      "diff": 76,
      "local_type_id": 2073,
      "local_province_id": 22
    },
    {
      "school_id": 2150,
      "name": "山东现代学院",
      "year": 2025,
      "local_batch_id": 14,
      "local_batch_name": "本科批",
      "local_province_name": "吉林",
      "local_type_name": "物理类",
      "min": 400,
      "min_section": 55396,
      "num": 6,
      "proscore": 340,
      "sg_info": "首选物理，再选化学",
      "sg_name": "（002）",
      "special_group": "482371",
      "xclevel_name": "",
      "zslx_name": "普通类",
      "diff": 60,
      "local_type_id": 2073,
      "local_province_id": 22
    },
    {
      "school_id": 2150,
      "name": "山东现代学院",
      "year": 2025,
      "local_batch_id": 14,
      "local_batch_name": "本科批",
      "local_province_name": "吉林",
      "local_type_name": "历史类",
      "min": 448,
      "min_section": 14158,
      "num": 2,
      "proscore": 384,
      "sg_info": "首选历史，再选不限",
      "sg_name": "（001）",
      "special_group": "482365",
      "xclevel_name": "",
      "zslx_name": "普通类",
      "diff": 64,
      "local_type_id": 2074,
      "local_province_id": 22
    },
    {
      "sp_name": "财务管理",
      "remark": "",
      "min": "393",
      "min_section": "72617",
      "average": "-",
      "is_score_range": 2,
      "min_range": "-",
      "min_rank_range": "-",
      "zslx_name": "普通类",
      "sg_info": "首选物理，再选不限",
      "diff": 33,
      "lq_num": "-",
      "sg_name": "（003）",
      "school_special_id": 159151,
      "school_special_status": 1,
      "local_type_id": 2073,
      "local_province_id": 23,
      "local_batch_id": 14
    },
    {
      "sp_name": "护理学",
      "remark": "",
      "min": "382",
      "min_section": "76944",
      "average": "-",
      "is_score_range": 2,
      "min_range": "-",
      "min_rank_range": "-",
      "zslx_name": "普通类",
      "sg_info": "首选物理，再选生物",
      "diff": 22,
      "lq_num": "-",
      "sg_name": "（005）",
      "school_special_id": 159138,
      "school_special_status": 1,
      "local_type_id": 2073,
      "local_province_id": 23,
      "local_batch_id": 14
    },
    {
      "sp_name": "数据科学与大数据技术",
      "remark": "",
      "min": "373",
      "min_section": "80466",
      "average": "-",
      "is_score_range": 2,
      "min_range": "-",
      "min_rank_range": "-",
      "zslx_name": "普通类",
      "sg_info": "首选物理，再选化学",
      "diff": 13,
      "lq_num": "-",
      "sg_name": "（004）",
      "school_special_id": 1130442,
      "school_special_status": 1,
      "local_type_id": 2073,
      "local_province_id": 23,
      "local_batch_id": 14
    },
    {
      "sp_name": "药学",
      "remark": "",
      "min": "369",
      "min_section": "81961",
      "average": "-",
      "is_score_range": 2,
      "min_range": "-",
      "min_rank_range": "-",
      "zslx_name": "普通类",
      "sg_info": "首选物理，再选化学",
      "diff": 9,
      "lq_num": "-",
      "sg_name": "（004）",
      "school_special_id": 159136,
      "school_special_status": 1,
      "local_type_id": 2073,
      "local_province_id": 23,
      "local_batch_id": 14
    },
    {
      "sp_name": "计算机科学与技术",
      "remark": "",
      "min": "368",
      "min_section": "82348",
      "average": "-",
      "is_score_range": 2,
      "min_range": "-",
      "min_rank_range": "-",
      "zslx_name": "普通类",
      "sg_info": "首选物理，再选化学",
      "diff": 8,
      "lq_num": "-",
      "sg_name": "（004）",
      "school_special_id": 159143,
      "school_special_status": 1,
      "local_type_id": 2073,
      "local_province_id": 23,
      "local_batch_id": 14
    },
    {
      "sp_name": "人工智能",
      "remark": "",
      "min": "366",
      "min_section": "83089",
      "average": "-",
      "is_score_range": 2,
      "min_range": "-",
      "min_rank_range": "-",
      "zslx_name": "普通类",
      "sg_info": "首选物理，再选化学",
      "diff": 6,
      "lq_num": "-",
      "sg_name": "（004）",
      "school_special_id": 1130441,
      "school_special_status": 1,
      "local_type_id": 2073,
      "local_province_id": 23,
      "local_batch_id": 14
    },
    {
      "sp_name": "康复治疗学",
      "remark": "",
      "min": "366",
      "min_section": "83089",
      "average": "-",
      "is_score_range": 2,
      "min_range": "-",
      "min_rank_range": "-",
      "zslx_name": "普通类",
      "sg_info": "首选物理，再选化学",
      "diff": 6,
      "lq_num": "-",
      "sg_name": "（004）",
      "school_special_id": 159148,
      "school_special_status": 1,
      "local_type_id": 2073,
      "local_province_id": 23,
      "local_batch_id": 14
    },
    {
      "sp_name": "中药学",
      "remark": "",
      "min": "365",
      "min_section": "83485",
      "average": "-",
      "is_score_range": 2,
      "min_range": "-",
      "min_rank_range": "-",
      "zslx_name": "普通类",
      "sg_info": "首选物理，再选化学",
      "diff": 5,
      "lq_num": "-",
      "sg_name": "（004）",
      "school_special_id": 169900,
      "school_special_status": 1,
      "local_type_id": 2073,
      "local_province_id": 23,
      "local_batch_id": 14
    },
    {
      "sp_name": "数字媒体技术",
      "remark": "",
      "min": "363",
      "min_section": "84193",
      "average": "-",
      "is_score_range": 2,
      "min_range": "-",
      "min_rank_range": "-",
      "zslx_name": "普通类",
      "sg_info": "首选物理，再选化学",
      "diff": 3,
      "lq_num": "-",
      "sg_name": "（004）",
      "school_special_id": 159145,
      "school_special_status": 1,
      "local_type_id": 2073,
      "local_province_id": 23,
      "local_batch_id": 14
    },
    {
      "sp_name": "医学检验技术",
      "remark": "",
      "min": "362",
      "min_section": "84594",
      "average": "-",
      "is_score_range": 2,
      "min_range": "-",
      "min_rank_range": "-",
      "zslx_name": "普通类",
      "sg_info": "首选物理，再选化学",
      "diff": 2,
      "lq_num": "-",
      "sg_name": "（004）",
      "school_special_id": 1130443,
      "school_special_status": 1,
      "local_type_id": 2073,
      "local_province_id": 23,
      "local_batch_id": 14
    },
    {
      "school_id": 2150,
      "name": "山东现代学院",
      "year": 2025,
      "local_batch_id": 14,
      "local_batch_name": "本科批",
      "local_province_name": "江苏",
      "local_type_name": "物理类",
      "min": 481,
      "min_section": 186727,
      "num": "-",
      "proscore": 463,
      "sg_info": "首选物理，再选不限",
      "sg_name": "（03）",
      "special_group": "551854",
      "xclevel_name": "",
      "zslx_name": "普通类",
      "diff": 18,
      "local_type_id": 2073,
      "local_province_id": 32
    },
    {
      "school_id": 2150,
      "name": "山东现代学院",
      "year": 2025,
      "local_batch_id": 14,
      "local_batch_name": "本科批",
      "local_province_name": "江苏",
      "local_type_name": "物理类",
      "min": 469,
      "min_section": 200008,
      "num": "-",
      "proscore": 463,
      "sg_info": "首选物理，再选化学",
      "sg_name": "（04）",
      "special_group": "551856",
      "xclevel_name": "",
      "zslx_name": "普通类",
      "diff": 6,
      "local_type_id": 2073,
      "local_province_id": 32
    },
    {
      "school_id": 2150,
      "name": "山东现代学院",
      "year": 2025,
      "local_batch_id": 10,
      "local_batch_name": "专科批",
      "local_province_name": "江苏",
      "local_type_name": "物理类",
      "min": 307,
      "min_section": 255226,
      "num": "-",
      "proscore": 220,
      "sg_info": "首选物理，再选不限",
      "sg_name": "（05）",
      "special_group": "551858",
      "xclevel_name": "",
      "zslx_name": "普通类",
      "diff": 87,
      "local_type_id": 2073,
      "local_province_id": 32
    },
    {
      "sp_name": "工程造价",
      "remark": "",
      "min": "334",
      "min_section": "252839",
      "average": "-",
      "is_score_range": 2,
      "min_range": "-",
      "min_rank_range": "-",
      "zslx_name": "普通类",
      "sg_info": "首选物理，再选不限",
      "diff": 114,
      "lq_num": "1",
      "sg_name": "（05）",
      "school_special_id": 72356,
      "school_special_status": 2,
      "local_type_id": 2073,
      "local_province_id": 32,
      "local_batch_id": 10
    },
    {
      "sp_name": "汽车制造与试验技术",
      "remark": "",
      "min": "315",
      "min_section": "254551",
      "average": "-",
      "is_score_range": 2,
      "min_range": "-",
      "min_rank_range": "-",
      "zslx_name": "普通类",
      "sg_info": "首选物理，再选不限",
      "diff": 95,
      "lq_num": "1",
      "sg_name": "（05）",
      "school_special_id": 1534664,
      "school_special_status": 2,
      "local_type_id": 2073,
      "local_province_id": 32,
      "local_batch_id": 10
    },
    {
      "sp_name": "计算机网络技术",
      "remark": "",
      "min": "314",
      "min_section": "254641",
      "average": "-",
      "is_score_range": 2,
      "min_range": "-",
      "min_rank_range": "-",
      "zslx_name": "普通类",
      "sg_info": "首选物理，再选不限",
      "diff": 94,
      "lq_num": "1",
      "sg_name": "（05）",
      "school_special_id": 72344,
      "school_special_status": 1,
      "local_type_id": 2073,
      "local_province_id": 32,
      "local_batch_id": 10
    },
    {
      "sp_name": "大数据与会计",
      "remark": "",
      "min": "312",
      "min_section": "254822",
      "average": "-",
      "is_score_range": 2,
      "min_range": "-",
      "min_rank_range": "-",
      "zslx_name": "普通类",
      "sg_info": "首选物理，再选不限",
      "diff": 92,
      "lq_num": "4",
      "sg_name": "（05）",
      "school_special_id": 1534665,
      "school_special_status": 2,
      "local_type_id": 2073,
      "local_province_id": 32,
      "local_batch_id": 10
    },
    {
      "sp_name": "计算机应用技术",
      "remark": "",
      "min": "307",
      "min_section": "255226",
      "average": "-",
      "is_score_range": 2,
      "min_range": "-",
      "min_rank_range": "-",
      "zslx_name": "普通类",
      "sg_info": "首选物理，再选不限",
      "diff": 87,
      "lq_num": "3",
      "sg_name": "（05）",
      "school_special_id": 72342,
      "school_special_status": 1,
      "local_type_id": 2073,
      "local_province_id": 32,
      "local_batch_id": 10
    },
    {
      "sp_name": "市场营销",
      "remark": "",
      "min": "496",
      "min_section": "49121",
      "average": "-",
      "is_score_range": 2,
      "min_range": "-",
      "min_rank_range": "-",
      "zslx_name": "普通类",
      "sg_info": "首选历史，再选不限",
      "diff": 14,
      "lq_num": "2",
      "sg_name": "（01）",
      "school_special_id": 159150,
      "school_special_status": 1,
      "local_type_id": 2074,
      "local_province_id": 32,
      "local_batch_id": 14
    },
    {
      "sp_name": "财务管理",
      "remark": "",
      "min": "496",
      "min_section": "49121",
      "average": "-",
      "is_score_range": 2,
      "min_range": "-",
      "min_rank_range": "-",
      "zslx_name": "普通类",
      "sg_info": "首选历史，再选不限",
      "diff": 14,
      "lq_num": "20",
      "sg_name": "（01）",
      "school_special_id": 159151,
      "school_special_status": 1,
      "local_type_id": 2074,
      "local_province_id": 32,
      "local_batch_id": 14
    },
    {
      "school_id": 2150,
      "name": "山东现代学院",
      "year": 2025,
      "local_batch_id": 1570,
      "local_batch_name": "普通类一段",
      "local_province_name": "浙江",
      "local_type_name": "综合",
      "min": 493,
      "min_section": 180064,
      "num": "-",
      "proscore": "-",
      "sg_info": "",
      "sg_name": "",
      "special_group": "0",
      "xclevel_name": "",
      "zslx_name": "普通类",
      "diff": "-",
      "local_type_id": 3,
      "local_province_id": 33
    },
    {
      "school_id": 2150,
      "name": "山东现代学院",
      "year": 2025,
      "local_batch_id": 1571,
      "local_batch_name": "普通类二段",
      "local_province_name": "浙江",
      "local_type_name": "综合",
      "min": 317,
      "min_section": 281642,
      "num": "-",
      "proscore": 268,
      "sg_info": "",
      "sg_name": "",
      "special_group": "0",
      "xclevel_name": "",
      "zslx_name": "普通类",
      "diff": 49,
      "local_type_id": 3,
      "local_province_id": 33
    },
    {
      "school_id": 2150,
      "name": "山东现代学院",
      "year": 2025,
      "local_batch_id": 1570,
      "local_batch_name": "普通类一段",
      "local_province_name": "浙江",
      "local_type_name": "综合",
      "min": 492,
      "min_section": 181374,
      "num": "-",
      "proscore": "-",
      "sg_info": "",
      "sg_name": "",
      "special_group": "0",
      "xclevel_name": "",
      "zslx_name": "护理类",
      "diff": "-",
      "local_type_id": 3,
      "local_province_id": 33
    },
    {
      "school_id": 2150,
      "name": "山东现代学院",
      "year": 2025,
      "local_batch_id": 1571,
      "local_batch_name": "普通类二段",
      "local_province_name": "浙江",
      "local_type_name": "综合",
      "min": 405,
      "min_section": 251845,
      "num": "-",
      "proscore": 268,
      "sg_info": "",
      "sg_name": "",
      "special_group": "0",
      "xclevel_name": "",
      "zslx_name": "护理类",
      "diff": 137,
      "local_type_id": 3,
      "local_province_id": 33
    },
    {
      "sp_name": "护理",
      "remark": "",
      "min": "338",
      "min_section": "295747",
      "average": "342",
      "is_score_range": 2,
      "min_range": "-",
      "min_rank_range": "-",
      "zslx_name": "普通类",
      "sg_info": "首选物理，再选不限",
      "diff": 138,
      "lq_num": "-",
      "sg_name": "（004）",
      "school_special_id": 72350,
      "school_special_status": 1,
      "local_type_id": 2073,
      "local_province_id": 34,
      "local_batch_id": 10
    },
    {
      "sp_name": "口腔医学",
      "remark": "",
      "min": "329",
      "min_section": "299341",
      "average": "375",
      "is_score_range": 2,
      "min_range": "-",
      "min_rank_range": "-",
      "zslx_name": "普通类",
      "sg_info": "首选物理，再选不限",
      "diff": 129,
      "lq_num": "-",
      "sg_name": "（004）",
      "school_special_id": 1370404,
      "school_special_status": 1,
      "local_type_id": 2073,
      "local_province_id": 34,
      "local_batch_id": 10
    },
    {
      "sp_name": "针灸推拿",
      "remark": "",
      "min": "328",
      "min_section": "299733",
      "average": "360",
      "is_score_range": 2,
      "min_range": "-",
      "min_rank_range": "-",
      "zslx_name": "普通类",
      "sg_info": "首选物理，再选不限",
      "diff": 128,
      "lq_num": "-",
      "sg_name": "（004）",
      "school_special_id": 1023324,
      "school_special_status": 2,
      "local_type_id": 2073,
      "local_province_id": 34,
      "local_batch_id": 10
    },
    {
      "sp_name": "计算机网络技术",
      "remark": "",
      "min": "324",
      "min_section": "301213",
      "average": "324",
      "is_score_range": 2,
      "min_range": "-",
      "min_rank_range": "-",
      "zslx_name": "普通类",
      "sg_info": "首选物理，再选不限",
      "diff": 124,
      "lq_num": "-",
      "sg_name": "（004）",
      "school_special_id": 72344,
      "school_special_status": 1,
      "local_type_id": 2073,
      "local_province_id": 34,
      "local_batch_id": 10
    },
    {
      "sp_name": "计算机应用技术",
      "remark": "",
      "min": "313",
      "min_section": "304868",
      "average": "313",
      "is_score_range": 2,
      "min_range": "-",
      "min_rank_range": "-",
      "zslx_name": "普通类",
      "sg_info": "首选物理，再选不限",
      "diff": 113,
      "lq_num": "-",
      "sg_name": "（004）",
      "school_special_id": 72342,
      "school_special_status": 1,
      "local_type_id": 2073,
      "local_province_id": 34,
      "local_batch_id": 10
    },
    {
      "sp_name": "临床医学",
      "remark": "",
      "min": "313",
      "min_section": "304868",
      "average": "329",
      "is_score_range": 2,
      "min_range": "-",
      "min_rank_range": "-",
      "zslx_name": "普通类",
      "sg_info": "首选物理，再选不限",
      "diff": 113,
      "lq_num": "-",
      "sg_name": "（004）",
      "school_special_id": 72352,
      "school_special_status": 1,
      "local_type_id": 2073,
      "local_province_id": 34,
      "local_batch_id": 10
    },
    {
      "sp_name": "汉语国际教育",
      "remark": "",
      "min": "485",
      "min_section": "40761",
      "average": "485",
      "is_score_range": 2,
      "min_range": "-",
      "min_rank_range": "-",
      "zslx_name": "普通类",
      "sg_info": "首选历史，再选不限",
      "diff": 8,
      "lq_num": "-",
      "sg_name": "（001）",
      "school_special_id": 159140,
      "school_special_status": 1,
      "local_type_id": 2074,
      "local_province_id": 34,
      "local_batch_id": 14
    },
    {
      "sp_name": "市场营销",
      "remark": "",
      "min": "484",
      "min_section": "41258",
      "average": "484",
      "is_score_range": 2,
      "min_range": "-",
      "min_rank_range": "-",
      "zslx_name": "普通类",
      "sg_info": "首选历史，再选不限",
      "diff": 7,
      "lq_num": "-",
      "sg_name": "（001）",
      "school_special_id": 159150,
      "school_special_status": 1,
      "local_type_id": 2074,
      "local_province_id": 34,
      "local_batch_id": 14
    },
    {
      "sp_name": "财务管理",
      "remark": "",
      "min": "484",
      "min_section": "41258",
      "average": "484",
      "is_score_range": 2,
      "min_range": "-",
      "min_rank_range": "-",
      "zslx_name": "普通类",
      "sg_info": "首选历史，再选不限",
      "diff": 7,
      "lq_num": "-",
      "sg_name": "（001）",
      "school_special_id": 159151,
      "school_special_status": 1,
      "local_type_id": 2074,
      "local_province_id": 34,
      "local_batch_id": 14
    },
    {
      "sp_name": "学前教育",
      "remark": "（师范）",
      "min": "482",
      "min_section": "42281",
      "average": "483",
      "is_score_range": 2,
      "min_range": "-",
      "min_rank_range": "-",
      "zslx_name": "普通类",
      "sg_info": "首选历史，再选不限",
      "diff": 5,
      "lq_num": "-",
      "sg_name": "（001）",
      "school_special_id": 159135,
      "school_special_status": 1,
      "local_type_id": 2074,
      "local_province_id": 34,
      "local_batch_id": 14
    },
    {
      "school_id": 2150,
      "name": "山东现代学院",
      "year": 2025,
      "local_batch_id": 14,
      "local_batch_name": "本科批",
      "local_province_name": "河南",
      "local_type_name": "历史类",
      "min": 481,
      "min_section": 80334,
      "num": "-",
      "proscore": 471,
      "sg_info": "首选历史，再选不限",
      "sg_name": "（105）",
      "special_group": "506216",
      "xclevel_name": "",
      "zslx_name": "普通类",
      "diff": 10,
      "local_type_id": 2074,
      "local_province_id": 41
    },
    {
      "school_id": 2150,
      "name": "山东现代学院",
      "year": 2025,
      "local_batch_id": 10,
      "local_batch_name": "专科批",
      "local_province_name": "河南",
      "local_type_name": "历史类",
      "min": 378,
      "min_section": 201478,
      "num": 2,
      "proscore": 185,
      "sg_info": "首选历史，再选不限",
      "sg_name": "（102）",
      "special_group": "506208",
      "xclevel_name": "",
      "zslx_name": "普通类",
      "diff": 193,
      "local_type_id": 2074,
      "local_province_id": 41
    },
    {
      "school_id": 2150,
      "name": "山东现代学院",
      "year": 2025,
      "local_batch_id": 10,
      "local_batch_name": "专科批",
      "local_province_name": "河南",
      "local_type_name": "历史类",
      "min": 337,
      "min_section": 253668,
      "num": 19,
      "proscore": 185,
      "sg_info": "首选历史，再选不限",
      "sg_name": "（101）",
      "special_group": "506195",
      "xclevel_name": "",
      "zslx_name": "普通类",
      "diff": 152,
      "local_type_id": 2074,
      "local_province_id": 41
    },
    {
      "sp_name": "土木工程",
      "remark": "",
      "min": "484",
      "min_section": "240777",
      "average": "484",
      "is_score_range": 2,
      "min_range": "-",
      "min_rank_range": "-",
      "zslx_name": "普通类",
      "sg_info": "首选物理，再选化学",
      "diff": 57,
      "lq_num": "1",
      "sg_name": "（101）",
      "school_special_id": 159146,
      "school_special_status": 1,
      "local_type_id": 2073,
      "local_province_id": 41,
      "local_batch_id": 14
    },
    {
      "sp_name": "汉语国际教育",
      "remark": "",
      "min": "458",
      "min_section": "291419",
      "average": "458",
      "is_score_range": 2,
      "min_range": "-",
      "min_rank_range": "-",
      "zslx_name": "普通类",
      "sg_info": "首选物理，再选不限",
      "diff": 31,
      "lq_num": "1",
      "sg_name": "（104）",
      "school_special_id": 159140,
      "school_special_status": 1,
      "local_type_id": 2073,
      "local_province_id": 41,
      "local_batch_id": 14
    },
    {
      "sp_name": "中药制药",
      "remark": "",
      "min": "455",
      "min_section": "297074",
      "average": "457",
      "is_score_range": 2,
      "min_range": "-",
      "min_rank_range": "-",
      "zslx_name": "普通类",
      "sg_info": "首选物理，再选化学",
      "diff": 28,
      "lq_num": "2",
      "sg_name": "（101）",
      "school_special_id": 159137,
      "school_special_status": 1,
      "local_type_id": 2073,
      "local_province_id": 41,
      "local_batch_id": 14
    },
    {
      "sp_name": "人工智能",
      "remark": "",
      "min": "449",
      "min_section": "308332",
      "average": "460",
      "is_score_range": 2,
      "min_range": "-",
      "min_rank_range": "-",
      "zslx_name": "普通类",
      "sg_info": "首选物理，再选化学",
      "diff": 22,
      "lq_num": "7",
      "sg_name": "（101）",
      "school_special_id": 1130441,
      "school_special_status": 1,
      "local_type_id": 2073,
      "local_province_id": 41,
      "local_batch_id": 14
    },
    {
      "sp_name": "数据科学与大数据技术",
      "remark": "",
      "min": "449",
      "min_section": "308332",
      "average": "451",
      "is_score_range": 2,
      "min_range": "-",
      "min_rank_range": "-",
      "zslx_name": "普通类",
      "sg_info": "首选物理，再选化学",
      "diff": 22,
      "lq_num": "4",
      "sg_name": "（101）",
      "school_special_id": 1130442,
      "school_special_status": 1,
      "local_type_id": 2073,
      "local_province_id": 41,
      "local_batch_id": 14
    },
    {
      "sp_name": "药学",
      "remark": "",
      "min": "449",
      "min_section": "308332",
      "average": "451",
      "is_score_range": 2,
      "min_range": "-",
      "min_rank_range": "-",
      "zslx_name": "普通类",
      "sg_info": "首选物理，再选化学",
      "diff": 22,
      "lq_num": "5",
      "sg_name": "（101）",
      "school_special_id": 159136,
      "school_special_status": 1,
      "local_type_id": 2073,
      "local_province_id": 41,
      "local_batch_id": 14
    },
    {
      "sp_name": "汽车服务工程",
      "remark": "",
      "min": "448",
      "min_section": "310147",
      "average": "452",
      "is_score_range": 2,
      "min_range": "-",
      "min_rank_range": "-",
      "zslx_name": "普通类",
      "sg_info": "首选物理，再选化学",
      "diff": 21,
      "lq_num": "3",
      "sg_name": "（101）",
      "school_special_id": 159141,
      "school_special_status": 1,
      "local_type_id": 2073,
      "local_province_id": 41,
      "local_batch_id": 14
    },
    {
      "sp_name": "电子信息工程",
      "remark": "",
      "min": "448",
      "min_section": "310147",
      "average": "450",
      "is_score_range": 2,
      "min_range": "-",
      "min_rank_range": "-",
      "zslx_name": "普通类",
      "sg_info": "首选物理，再选化学",
      "diff": 21,
      "lq_num": "6",
      "sg_name": "（101）",
      "school_special_id": 159142,
      "school_special_status": 1,
      "local_type_id": 2073,
      "local_province_id": 41,
      "local_batch_id": 14
    },
    {
      "sp_name": "中药学",
      "remark": "",
      "min": "448",
      "min_section": "310147",
      "average": "458",
      "is_score_range": 2,
      "min_range": "-",
      "min_rank_range": "-",
      "zslx_name": "普通类",
      "sg_info": "首选物理，再选化学",
      "diff": 21,
      "lq_num": "5",
      "sg_name": "（101）",
      "school_special_id": 169900,
      "school_special_status": 1,
      "local_type_id": 2073,
      "local_province_id": 41,
      "local_batch_id": 14
    },
    {
      "sp_name": "护理学",
      "remark": "",
      "min": "448",
      "min_section": "310147",
      "average": "452",
      "is_score_range": 2,
      "min_range": "-",
      "min_rank_range": "-",
      "zslx_name": "普通类",
      "sg_info": "首选物理，再选生物",
      "diff": 21,
      "lq_num": "16",
      "sg_name": "（102）",
      "school_special_id": 159138,
      "school_special_status": 1,
      "local_type_id": 2073,
      "local_province_id": 41,
      "local_batch_id": 14
    },
    {
      "sp_name": "财务管理",
      "remark": "（办学地点：校本部）",
      "min": "468",
      "min_section": "26437",
      "average": "-",
      "is_score_range": 2,
      "min_range": "-",
      "min_rank_range": "-",
      "zslx_name": "普通类",
      "sg_info": "首选历史，再选不限",
      "diff": 30,
      "lq_num": "-",
      "school_special_id": 159151,
      "school_special_status": 1,
      "local_type_id": 2074,
      "local_province_id": 50,
      "local_batch_id": 14
    },
    {
      "sp_name": "学前教育",
      "remark": "（师范类）（办学地点：校本部）",
      "min": "458",
      "min_section": "29374",
      "average": "-",
      "is_score_range": 2,
      "min_range": "-",
      "min_rank_range": "-",
      "zslx_name": "普通类",
      "sg_info": "首选历史，再选不限",
      "diff": 20,
      "lq_num": "-",
      "school_special_id": 159135,
      "school_special_status": 1,
      "local_type_id": 2074,
      "local_province_id": 50,
      "local_batch_id": 14
    },
    {
      "sp_name": "汉语国际教育",
      "remark": "（办学地点：校本部）",
      "min": "458",
      "min_section": "29374",
      "average": "-",
      "is_score_range": 2,
      "min_range": "-",
      "min_rank_range": "-",
      "zslx_name": "普通类",
      "sg_info": "首选历史，再选不限",
      "diff": 20,
      "lq_num": "-",
      "school_special_id": 159140,
      "school_special_status": 1,
      "local_type_id": 2074,
      "local_province_id": 50,
      "local_batch_id": 14
    },
    {
      "sp_name": "市场营销",
      "remark": "（办学地点：校本部）",
      "min": "445",
      "min_section": "33174",
      "average": "-",
      "is_score_range": 2,
      "min_range": "-",
      "min_rank_range": "-",
      "zslx_name": "普通类",
      "sg_info": "首选历史，再选不限",
      "diff": 7,
      "lq_num": "-",
      "school_special_id": 159150,
      "school_special_status": 1,
      "local_type_id": 2074,
      "local_province_id": 50,
      "local_batch_id": 14
    },
    {
      "school_id": 2150,
      "name": "山东现代学院",
      "year": 2025,
      "local_batch_id": 47,
      "local_batch_name": "本科批B段",
      "local_province_name": "宁夏",
      "local_type_name": "历史类",
      "min": 422,
      "min_section": 7776,
      "num": "-",
      "proscore": 404,
      "sg_info": "首选历史，再选不限",
      "sg_name": "（001）",
      "special_group": "608207",
      "xclevel_name": "",
      "zslx_name": "普通类",
      "diff": 18,
      "local_type_id": 2074,
      "local_province_id": 64
    },
    {
      "school_id": 2150,
      "name": "山东现代学院",
      "year": 2025,
      "local_batch_id": 8,
      "local_batch_name": "本科二批",
      "local_province_name": "新疆",
      "local_type_name": "文科",
      "min": 338,
      "min_section": 13672,
      "num": 7,
      "proscore": 330,
      "sg_info": "",
      "sg_name": "",
      "special_group": "0",
      "xclevel_name": "",
      "zslx_name": "普通类",
      "diff": 8,
      "local_type_id": 2,
      "local_province_id": 65
    },
    {
      "sp_name": "护理学",
      "remark": "",
      "min": "354",
      "min_section": "12075",
      "average": "355",
      "is_score_range": 2,
      "min_range": "-",
      "min_rank_range": "-",
      "zslx_name": "普通类",
      "sg_info": "",
      "diff": 24,
      "lq_num": "2",
      "school_special_id": 159138,
      "school_special_status": 1,
      "local_type_id": 2,
      "local_province_id": 65,
      "local_batch_id": 8
    },
    {
      "sp_name": "康复治疗学",
      "remark": "",
      "min": "346",
      "min_section": "12885",
      "average": "346",
      "is_score_range": 2,
      "min_range": "-",
      "min_rank_range": "-",
      "zslx_name": "普通类",
      "sg_info": "",
      "diff": 16,
      "lq_num": "1",
      "school_special_id": 159148,
      "school_special_status": 1,
      "local_type_id": 2,
      "local_province_id": 65,
      "local_batch_id": 8
    },
    {
      "sp_name": "中药学",
      "remark": "",
      "min": "342",
      "min_section": "13270",
      "average": "352",
      "is_score_range": 2,
      "min_range": "-",
      "min_rank_range": "-",
      "zslx_name": "普通类",
      "sg_info": "",
      "diff": 12,
      "lq_num": "2",
      "school_special_id": 169900,
      "school_special_status": 1,
      "local_type_id": 2,
      "local_province_id": 65,
      "local_batch_id": 8
    },
    {
      "sp_name": "医学检验技术",
      "remark": "",
      "min": "338",
      "min_section": "13672",
      "average": "341",
      "is_score_range": 2,
      "min_range": "-",
      "min_rank_range": "-",
      "zslx_name": "普通类",
      "sg_info": "",
      "diff": 8,
      "lq_num": "2",
      "school_special_id": 1130443,
      "school_special_status": 1,
      "local_type_id": 2,
      "local_province_id": 65,
      "local_batch_id": 8
    }
  ]
}